Workbook
Name v: 'Ряд'!$H$5:$H$40
Name d: 'Ряд'!$J$6:$J$40
Name cor_kb: 'Ряд'!$O$5:$O$40
Name d_cor_kb: 'Ряд'!$P$6:$P$40
Name cor_ms: 'Ряд'!$R$5:$R$40
Name d_cor_ms: 'Ряд'!$S$6:$S$40
Name p_conf: 'Параметры'!$C$5
Name z_p: 'Параметры'!$C$6
Name k_G26: 'Параметры'!$C$7
Name L_reg: 'Параметры'!$C$8
Name T_cikl: 'Параметры'!$C$9
Name por_sk: 'Параметры'!$C$10
Name por_zaim: 'Параметры'!$C$11
Name alpha: 'Параметры'!$C$12
Name ad_crit: 'Параметры'!$C$13
Name tau: 'Параметры'!$C$14

Sheet Как защищать
A1: Расчётный лист по топ-20: как им пользоваться на комитете
A2: Редакция 15.09.2026, восьмая. Собрано из data/top20_monthly_2023_08_2026_07.csv сборщиком build/raschet_list.py — правки вносятся в скрипт, а не в готовый файл. Сверка: python3 raschet_list.py --verify.
A4: АНАЛИТИЧЕСКАЯ ПОВЕСТКА: что на что делится | B4: Книга отвечает на три РАЗНЫХ вопроса, и смешивать их нельзя. (1) КАКОЙ УРОВЕНЬ ГОТОВЫ ДЕРЖАТЬ — это риск-аппетит, он задаётся не волатильностью, а выживаемостью в сценарии; разбор вынесен в STRESS_ANCHOR.md. (2) КОГДА СМОТРЕТЬ ЧАЩЕ — это ЗОНА, и вся книга про неё. (3) КОГДА ДЕЙСТВОВАТЬ — это ТРИГГЕР, он смотрит на движение, а не на уровень. Зона и триггер ловят разное: январский вход топ-20 в красную сделан капиталом, и уровневая зона не предупреждала о нём в принципе.
A5: РАЗВИЛКА МЕТОДА: как выбирается формула зоны | B5: Сначала проверяется, подчиняются ли приращения метрики нормальному распределению — лист «Расчёт», блок 8. Но формальная проверка НЕ решает: M(T) опирается не на приращение, а на СУММУ T приращений, которая по центральной предельной теореме ближе к нормальной. Решает вторая проверка — совпадает ли модельный квантиль z·σ·√T с фактическим 90-м процентилем реальных T-месячных изменений. Вердикт четырёхзначный, и направление расхождения важнее величины: СОВПАДАЕТ → M(T); МОДЕЛЬ ЗАВЫШАЕТ → M(T) годится, она консервативна, завышение объявляется; МОДЕЛЬ ЗАНИЖАЕТ → опасно, нужна замена; БУФЕР БОЛЬШЕ САМОГО ЛИМИТА → зона вырождается, метод непригоден по полезности. На нашем ряде: одиннадцать метрик на M(T), одна на замене.
A6: ДВА МЕТОДА И ИХ ИСТОЧНИКИ | B6: Первый — запас времени M(T) = z(p)·σ_Δ·√T. Параметрический буфер на диффузию; то же построение, что у параметрического VaR. Обоснование — лист «Обоснование методов», блоки 1–4: независимость приращений, нормальность суммы, отсутствие сноса, устойчивость σ. Второй — эмпирический 90-й процентиль фактических T-месячных изменений, то есть историческая симуляция: BCBS d457 (MAR30) допускает её наравне с параметрической моделью, и при тяжёлых хвостах она в практике преобладает. Обоснование — блок 5 того же листа. Названия зон и их смысл — дословно п. 18 Правил № 86, своих формулировок нет.
A7: Что в книге | B7: «Ряд» — 36 точек и всё, что считается построчно, обе базы капитала рядом, плюс режимные колонки T–AF (фев-март против остальных месяцев, Г36). «Параметры» — десять входов, из них вычисляются два; там же α, A²_крит и τ проверки нормальности. «Расчёт» — каждое опубликованное число живой формулой, блок 8 — проверка нормальности по каждой из двенадцати метрик. «Обоснование методов» — блоки 1–4 про M(T), блок 5 про её замену. «Зоны» — разметка топ-20 и где мы сейчас. «Две сигмы» — остаток Р-Д1. «Триггеры» — все 35 приростов топ-20 и два универсальных триггера по каждой из двенадцати метрик. «Метрики» — ВСЕ зоны на одной странице, с колонками «чем и почему посчитано».
A8: Главное свойство | B8: В книге нет ни одного вбитого руками результата, кроме одного помеченного (бутстрап). Любое число со слайда выделяется в колонке «Значение», и в строке формул видно, из чего оно получено. Несогласный с параметром меняет его на листе «Параметры», и вся книга пересчитывается при нём.
A9: «Откуда 108,63» | B9: Уровень 95 % задан в регуляторной базе капитала. С 01.01.2026 знаменатель метрики — балансовый капитал (Г26), k = 0,8745 есть отношение баз. 108,63 — тот же уровень в новой базе. Второй, независимый путь: квантиль 90 % ряда плюс запас на три месяца даёт 108,58. Сходимость двух путей на 0,05 пп и есть довод, что уровень не подогнан.
A10: «Почему корень из T» | B10: Складываются дисперсии, а не с.к.о.: сумма T независимых приростов имеет дисперсию T·σ², то есть разброс σ·√T. Держится это ровно на независимости. Лист «Обоснование M(T)», блок 1: автокорреляция −0,08 при пороге 0,34; фактический разброс трёхмесячных изменений 6,40 против модельных 7,04 — модель ЗАВЫШАЕТ, то есть ошибается в безопасную сторону.
A11: «Почему нормальное распределение» | B11: Нужна нормальность не приростов, а их трёхмесячной СУММЫ, к которой буфер и применяется. У приростов асимметрия 0,67, у суммы — 0,04. Жарк–Бера на приростах 2,70 при критических 5,99. И z(0,90) = 1,28 лежит в теле распределения, а не в хвосте: ошибки нормальности бьют на 99 %, не на 90 %. Лист «Обоснование методов», блок 2.
A12: «А буфер не выдуман» | B12: Три непараметрических способа дают 9,29, 9,35 и 9,37 против модельных 9,03 — разброс 3,6 % при собственной погрешности σ в ±1,09. И проверка на факте: движение апрель→июль 2026 составило +8,24 пп, то есть 91 % буфера. Буфер не подушка на всякий случай — ряд только что прошёл почти ровно такое движение.
A13: «Почему T = 3» | B13: Честный ответ: длина цикла решения не измерена и в регламенте не закреплена. Это записано как незакрытый пункт, а не спрятано. Поставьте на «Параметрах» T = 2 или T = 4 — уровень двигается примерно на 1,4–1,5 пп за месяц цикла.
A14: «Почему 90 %, а не 95 или 99» | B14: Это цена ложного отбоя, а не расчёт. При 90 % один ложный сигнал из десяти. Выше — жёлтая опускается и лампа горит почти всегда. Параметр p на листе «Параметры» меняется, z пересчитывается сам. Решение комитета, не наше.
A15: «Где мы сейчас» | B15: Лист «Зоны». Текущая точка 101,50 — жёлтая зона. До лимита 7,13 пп = 1,75 σ. T* = 1,87 месяца: столько остаётся до лимита при доверии 90 %. Красная зона за 36 месяцев загоралась один раз, пробоев не было ни разу.
A16: «А если ничего не менять» | B16: Лист «Расчёт», блок 7. При сохранении уровня 95 % жёлтая линия ложится на 85,97, и выше неё оказывается 31 наблюдение из 36. Светофор с постоянно горящей лампой не является системой раннего предупреждения.
A17: Цепочка «риск-ёмкость → риск-аппетит → лимит → допустимый уровень → мера реагирования → контроль» и её фактические разрывы: целиком есть одно звено из шести.
A18: Чего книга не доказывает | B18: Что формулы верны по существу. Она доказывает ровно одно: числа получены из ряда объявленными формулами, а допущения формулы буфера проверены на этом же ряде и не отвергнуты. Верна ли метрика и тот ли это ряд — из воспроизводимости не следует.

Sheet Ряд
A1: Ряд топ-20: 36 месячных точек, 01.08.2023 — 01.07.2026
A2: Источник: data/top20_monthly_2023_08_2026_07.csv, дамп листа Monthly рабочей книги 08.09.2026 (DECOMPOSITION § 11.7). Колонки A–D — как в выгрузке, E–M — расчёт. С 01.02.2026 регуляторный капитал в выгрузке отсутствует: метрика ведётся только в балансовой базе, поэтому C, E, F и I у последних шести дат пусты. Это не пропуск данных, а следствие смены базы (Г26). Колонки N–S — CoR по КБ/ПБ и по МСБ из того же файла, 36 из 36: в первой сборке листа «Метрики» они были ошибочно взяты из квартального ряда.
A4: Дата | B4: Займ топ-20, млн ₸ | C4: СК регуляторный, млн ₸ | D4: СК балансовый, млн ₸ | E4: coef_reg (доля) | F4: v_reg = coef_reg × 100 | G4: coef_new (доля) | H4: v_new = coef_new × 100 | I4: Разрыв баз: v_new − v_reg | J4: Δ = v_new(t) − v_new(t−1) | K4: ΔСК балансовый, % | L4: ΔЗайм, % | M4: Триггер | N4: cor_kb_pb (доля) | O4: CoR КБ/ПБ, % | P4: Δ CoR КБ/ПБ | Q4: cor_msb (доля) | R4: CoR МСБ, % | S4: Δ CoR МСБ | T4: Окно закрытия? (фев/март) | U4: Δ КБ/ПБ обычн. | V4: Δ КБ/ПБ закр. | W4: Изм. КБ/ПБ за 4 мес | X4: Окно 4 мес задело закрытие? | Y4: 4 мес КБ/ПБ обычн. | Z4: 4 мес КБ/ПБ закр. | AA4: Δ МСБ обычн. | AB4: Δ МСБ закр. | AC4: Изм. МСБ за 4 мес | AD4: 4 мес МСБ обычн. | AE4: 4 мес МСБ закр. | AF4: Изм. топ-20 за 4 мес
A5: 2023-08-01 | B5: 323730.9 | C5: 413937.12 | D5: 322505.42 | E5: =IF(C5="","",B5/C5) | F5: =IF(E5="","",E5*100) | G5: =B5/D5 | H5: =G5*100 | I5: =IF(F5="","",H5-F5) | J5: — | K5: — | L5: — | M5: — | N5: 0.022715299 | O5: =N5*100 | P5: — | Q5: -0.00014823711 | R5: =Q5*100 | S5: — | T5: =IF(OR(MID(A5,6,2)="02",MID(A5,6,2)="03"),1,0) | U5: — | V5: — | W5: — | X5: — | Y5: — | Z5: — | AA5: — | AB5: — | AC5: — | AD5: — | AE5: — | AF5: —
A6: 2023-09-01 | B6: 323218.4 | C6: 422472.24 | D6: 331426.59 | E6: =IF(C6="","",B6/C6) | F6: =IF(E6="","",E6*100) | G6: =B6/D6 | H6: =G6*100 | I6: =IF(F6="","",H6-F6) | J6: =H6-H5 | K6: =(D6-D5)/D5*100 | L6: =(B6-B5)/B5*100 | M6: =IF(AND(K6<=por_sk,L6>=por_zaim),"оба",IF(K6<=por_sk,"СК",IF(L6>=por_zaim,"Займ",""))) | N6: 0.018498312 | O6: =N6*100 | P6: =O6-O5 | Q6: -0.0057911412 | R6: =Q6*100 | S6: =R6-R5 | T6: =IF(OR(MID(A6,6,2)="02",MID(A6,6,2)="03"),1,0) | U6: =IF(T6=0,P6,"") | V6: =IF(T6=1,P6,"") | W6: — | X6: — | Y6: — | Z6: — | AA6: =IF(T6=0,S6,"") | AB6: =IF(T6=1,S6,"") | AC6: — | AD6: — | AE6: — | AF6: —
A7: 2023-10-01 | B7: 327285 | C7: 429717.91 | D7: 339057.93 | E7: =IF(C7="","",B7/C7) | F7: =IF(E7="","",E7*100) | G7: =B7/D7 | H7: =G7*100 | I7: =IF(F7="","",H7-F7) | J7: =H7-H6 | K7: =(D7-D6)/D6*100 | L7: =(B7-B6)/B6*100 | M7: =IF(AND(K7<=por_sk,L7>=por_zaim),"оба",IF(K7<=por_sk,"СК",IF(L7>=por_zaim,"Займ",""))) | N7: 0.011475888 | O7: =N7*100 | P7: =O7-O6 | Q7: -0.0078013312 | R7: =Q7*100 | S7: =R7-R6 | T7: =IF(OR(MID(A7,6,2)="02",MID(A7,6,2)="03"),1,0) | U7: =IF(T7=0,P7,"") | V7: =IF(T7=1,P7,"") | W7: — | X7: — | Y7: — | Z7: — | AA7: =IF(T7=0,S7,"") | AB7: =IF(T7=1,S7,"") | AC7: — | AD7: — | AE7: — | AF7: —
A8: 2023-11-01 | B8: 338817.1 | C8: 438451.72 | D8: 348167.43 | E8: =IF(C8="","",B8/C8) | F8: =IF(E8="","",E8*100) | G8: =B8/D8 | H8: =G8*100 | I8: =IF(F8="","",H8-F8) | J8: =H8-H7 | K8: =(D8-D7)/D7*100 | L8: =(B8-B7)/B7*100 | M8: =IF(AND(K8<=por_sk,L8>=por_zaim),"оба",IF(K8<=por_sk,"СК",IF(L8>=por_zaim,"Займ",""))) | N8: 0.0021619168 | O8: =N8*100 | P8: =O8-O7 | Q8: -0.01204134 | R8: =Q8*100 | S8: =R8-R7 | T8: =IF(OR(MID(A8,6,2)="02",MID(A8,6,2)="03"),1,0) | U8: =IF(T8=0,P8,"") | V8: =IF(T8=1,P8,"") | W8: — | X8: — | Y8: — | Z8: — | AA8: =IF(T8=0,S8,"") | AB8: =IF(T8=1,S8,"") | AC8: — | AD8: — | AE8: — | AF8: —
A9: 2023-12-01 | B9: 343497.7 | C9: 443261.61 | D9: 353304.97 | E9: =IF(C9="","",B9/C9) | F9: =IF(E9="","",E9*100) | G9: =B9/D9 | H9: =G9*100 | I9: =IF(F9="","",H9-F9) | J9: =H9-H8 | K9: =(D9-D8)/D8*100 | L9: =(B9-B8)/B8*100 | M9: =IF(AND(K9<=por_sk,L9>=por_zaim),"оба",IF(K9<=por_sk,"СК",IF(L9>=por_zaim,"Займ",""))) | N9: -0.00076431654 | O9: =N9*100 | P9: =O9-O8 | Q9: -0.010726423 | R9: =Q9*100 | S9: =R9-R8 | T9: =IF(OR(MID(A9,6,2)="02",MID(A9,6,2)="03"),1,0) | U9: =IF(T9=0,P9,"") | V9: =IF(T9=1,P9,"") | W9: =O9-O5 | X9: =IF(SUM(T6:T9)>0,1,0) | Y9: =IF(X9=0,W9,"") | Z9: =IF(X9=1,W9,"") | AA9: =IF(T9=0,S9,"") | AB9: =IF(T9=1,S9,"") | AC9: =R9-R5 | AD9: =IF(X9=0,AC9,"") | AE9: =IF(X9=1,AC9,"") | AF9: =H9-H5
A10: 2024-01-01 | B10: 372019.3 | C10: 440898.15 | D10: 351291.9 | E10: =IF(C10="","",B10/C10) | F10: =IF(E10="","",E10*100) | G10: =B10/D10 | H10: =G10*100 | I10: =IF(F10="","",H10-F10) | J10: =H10-H9 | K10: =(D10-D9)/D9*100 | L10: =(B10-B9)/B9*100 | M10: =IF(AND(K10<=por_sk,L10>=por_zaim),"оба",IF(K10<=por_sk,"СК",IF(L10>=por_zaim,"Займ",""))) | N10: -0.019343434 | O10: =N10*100 | P10: =O10-O9 | Q10: -0.01082676 | R10: =Q10*100 | S10: =R10-R9 | T10: =IF(OR(MID(A10,6,2)="02",MID(A10,6,2)="03"),1,0) | U10: =IF(T10=0,P10,"") | V10: =IF(T10=1,P10,"") | W10: =O10-O6 | X10: =IF(SUM(T7:T10)>0,1,0) | Y10: =IF(X10=0,W10,"") | Z10: =IF(X10=1,W10,"") | AA10: =IF(T10=0,S10,"") | AB10: =IF(T10=1,S10,"") | AC10: =R10-R6 | AD10: =IF(X10=0,AC10,"") | AE10: =IF(X10=1,AC10,"") | AF10: =H10-H6
A11: 2024-02-01 | B11: 359821.6 | C11: 453740.46 | D11: 364498.16 | E11: =IF(C11="","",B11/C11) | F11: =IF(E11="","",E11*100) | G11: =B11/D11 | H11: =G11*100 | I11: =IF(F11="","",H11-F11) | J11: =H11-H10 | K11: =(D11-D10)/D10*100 | L11: =(B11-B10)/B10*100 | M11: =IF(AND(K11<=por_sk,L11>=por_zaim),"оба",IF(K11<=por_sk,"СК",IF(L11>=por_zaim,"Займ",""))) | N11: -0.076401161 | O11: =N11*100 | P11: =O11-O10 | Q11: -0.021314956 | R11: =Q11*100 | S11: =R11-R10 | T11: =IF(OR(MID(A11,6,2)="02",MID(A11,6,2)="03"),1,0) | U11: =IF(T11=0,P11,"") | V11: =IF(T11=1,P11,"") | W11: =O11-O7 | X11: =IF(SUM(T8:T11)>0,1,0) | Y11: =IF(X11=0,W11,"") | Z11: =IF(X11=1,W11,"") | AA11: =IF(T11=0,S11,"") | AB11: =IF(T11=1,S11,"") | AC11: =R11-R7 | AD11: =IF(X11=0,AC11,"") | AE11: =IF(X11=1,AC11,"") | AF11: =H11-H7
A12: 2024-03-01 | B12: 371215.4 | C12: 472963.53 | D12: 384072.88 | E12: =IF(C12="","",B12/C12) | F12: =IF(E12="","",E12*100) | G12: =B12/D12 | H12: =G12*100 | I12: =IF(F12="","",H12-F12) | J12: =H12-H11 | K12: =(D12-D11)/D11*100 | L12: =(B12-B11)/B11*100 | M12: =IF(AND(K12<=por_sk,L12>=por_zaim),"оба",IF(K12<=por_sk,"СК",IF(L12>=por_zaim,"Займ",""))) | N12: -0.047231984 | O12: =N12*100 | P12: =O12-O11 | Q12: -0.0051275576 | R12: =Q12*100 | S12: =R12-R11 | T12: =IF(OR(MID(A12,6,2)="02",MID(A12,6,2)="03"),1,0) | U12: =IF(T12=0,P12,"") | V12: =IF(T12=1,P12,"") | W12: =O12-O8 | X12: =IF(SUM(T9:T12)>0,1,0) | Y12: =IF(X12=0,W12,"") | Z12: =IF(X12=1,W12,"") | AA12: =IF(T12=0,S12,"") | AB12: =IF(T12=1,S12,"") | AC12: =R12-R8 | AD12: =IF(X12=0,AC12,"") | AE12: =IF(X12=1,AC12,"") | AF12: =H12-H8
A13: 2024-04-01 | B13: 363473 | C13: 484711.53 | D13: 396208.88 | E13: =IF(C13="","",B13/C13) | F13: =IF(E13="","",E13*100) | G13: =B13/D13 | H13: =G13*100 | I13: =IF(F13="","",H13-F13) | J13: =H13-H12 | K13: =(D13-D12)/D12*100 | L13: =(B13-B12)/B12*100 | M13: =IF(AND(K13<=por_sk,L13>=por_zaim),"оба",IF(K13<=por_sk,"СК",IF(L13>=por_zaim,"Займ",""))) | N13: -0.039429405 | O13: =N13*100 | P13: =O13-O12 | Q13: -0.010741815 | R13: =Q13*100 | S13: =R13-R12 | T13: =IF(OR(MID(A13,6,2)="02",MID(A13,6,2)="03"),1,0) | U13: =IF(T13=0,P13,"") | V13: =IF(T13=1,P13,"") | W13: =O13-O9 | X13: =IF(SUM(T10:T13)>0,1,0) | Y13: =IF(X13=0,W13,"") | Z13: =IF(X13=1,W13,"") | AA13: =IF(T13=0,S13,"") | AB13: =IF(T13=1,S13,"") | AC13: =R13-R9 | AD13: =IF(X13=0,AC13,"") | AE13: =IF(X13=1,AC13,"") | AF13: =H13-H9
A14: 2024-05-01 | B14: 357665.7 | C14: 489303.47 | D14: 401188.39 | E14: =IF(C14="","",B14/C14) | F14: =IF(E14="","",E14*100) | G14: =B14/D14 | H14: =G14*100 | I14: =IF(F14="","",H14-F14) | J14: =H14-H13 | K14: =(D14-D13)/D13*100 | L14: =(B14-B13)/B13*100 | M14: =IF(AND(K14<=por_sk,L14>=por_zaim),"оба",IF(K14<=por_sk,"СК",IF(L14>=por_zaim,"Займ",""))) | N14: -0.033388896 | O14: =N14*100 | P14: =O14-O13 | Q14: -0.0071952721 | R14: =Q14*100 | S14: =R14-R13 | T14: =IF(OR(MID(A14,6,2)="02",MID(A14,6,2)="03"),1,0) | U14: =IF(T14=0,P14,"") | V14: =IF(T14=1,P14,"") | W14: =O14-O10 | X14: =IF(SUM(T11:T14)>0,1,0) | Y14: =IF(X14=0,W14,"") | Z14: =IF(X14=1,W14,"") | AA14: =IF(T14=0,S14,"") | AB14: =IF(T14=1,S14,"") | AC14: =R14-R10 | AD14: =IF(X14=0,AC14,"") | AE14: =IF(X14=1,AC14,"") | AF14: =H14-H10
A15: 2024-06-01 | B15: 360756.5 | C15: 491481.95 | D15: 403780.01 | E15: =IF(C15="","",B15/C15) | F15: =IF(E15="","",E15*100) | G15: =B15/D15 | H15: =G15*100 | I15: =IF(F15="","",H15-F15) | J15: =H15-H14 | K15: =(D15-D14)/D14*100 | L15: =(B15-B14)/B14*100 | M15: =IF(AND(K15<=por_sk,L15>=por_zaim),"оба",IF(K15<=por_sk,"СК",IF(L15>=por_zaim,"Займ",""))) | N15: -0.024675437 | O15: =N15*100 | P15: =O15-O14 | Q15: -0.0065286648 | R15: =Q15*100 | S15: =R15-R14 | T15: =IF(OR(MID(A15,6,2)="02",MID(A15,6,2)="03"),1,0) | U15: =IF(T15=0,P15,"") | V15: =IF(T15=1,P15,"") | W15: =O15-O11 | X15: =IF(SUM(T12:T15)>0,1,0) | Y15: =IF(X15=0,W15,"") | Z15: =IF(X15=1,W15,"") | AA15: =IF(T15=0,S15,"") | AB15: =IF(T15=1,S15,"") | AC15: =R15-R11 | AD15: =IF(X15=0,AC15,"") | AE15: =IF(X15=1,AC15,"") | AF15: =H15-H11
A16: 2024-07-01 | B16: 362413.9 | C16: 492537.19 | D16: 405247.49 | E16: =IF(C16="","",B16/C16) | F16: =IF(E16="","",E16*100) | G16: =B16/D16 | H16: =G16*100 | I16: =IF(F16="","",H16-F16) | J16: =H16-H15 | K16: =(D16-D15)/D15*100 | L16: =(B16-B15)/B15*100 | M16: =IF(AND(K16<=por_sk,L16>=por_zaim),"оба",IF(K16<=por_sk,"СК",IF(L16>=por_zaim,"Займ",""))) | N16: -0.022446194 | O16: =N16*100 | P16: =O16-O15 | Q16: -0.0038854969 | R16: =Q16*100 | S16: =R16-R15 | T16: =IF(OR(MID(A16,6,2)="02",MID(A16,6,2)="03"),1,0) | U16: =IF(T16=0,P16,"") | V16: =IF(T16=1,P16,"") | W16: =O16-O12 | X16: =IF(SUM(T13:T16)>0,1,0) | Y16: =IF(X16=0,W16,"") | Z16: =IF(X16=1,W16,"") | AA16: =IF(T16=0,S16,"") | AB16: =IF(T16=1,S16,"") | AC16: =R16-R12 | AD16: =IF(X16=0,AC16,"") | AE16: =IF(X16=1,AC16,"") | AF16: =H16-H12
A17: 2024-08-01 | B17: 358163.4 | C17: 504710.47 | D17: 417859.74 | E17: =IF(C17="","",B17/C17) | F17: =IF(E17="","",E17*100) | G17: =B17/D17 | H17: =G17*100 | I17: =IF(F17="","",H17-F17) | J17: =H17-H16 | K17: =(D17-D16)/D16*100 | L17: =(B17-B16)/B16*100 | M17: =IF(AND(K17<=por_sk,L17>=por_zaim),"оба",IF(K17<=por_sk,"СК",IF(L17>=por_zaim,"Займ",""))) | N17: -0.021509859 | O17: =N17*100 | P17: =O17-O16 | Q17: -0.0044458864 | R17: =Q17*100 | S17: =R17-R16 | T17: =IF(OR(MID(A17,6,2)="02",MID(A17,6,2)="03"),1,0) | U17: =IF(T17=0,P17,"") | V17: =IF(T17=1,P17,"") | W17: =O17-O13 | X17: =IF(SUM(T14:T17)>0,1,0) | Y17: =IF(X17=0,W17,"") | Z17: =IF(X17=1,W17,"") | AA17: =IF(T17=0,S17,"") | AB17: =IF(T17=1,S17,"") | AC17: =R17-R13 | AD17: =IF(X17=0,AC17,"") | AE17: =IF(X17=1,AC17,"") | AF17: =H17-H13
A18: 2024-09-01 | B18: 379875.3 | C18: 507597.08 | D18: 421198.75 | E18: =IF(C18="","",B18/C18) | F18: =IF(E18="","",E18*100) | G18: =B18/D18 | H18: =G18*100 | I18: =IF(F18="","",H18-F18) | J18: =H18-H17 | K18: =(D18-D17)/D17*100 | L18: =(B18-B17)/B17*100 | M18: =IF(AND(K18<=por_sk,L18>=por_zaim),"оба",IF(K18<=por_sk,"СК",IF(L18>=por_zaim,"Займ",""))) | N18: -0.021547681 | O18: =N18*100 | P18: =O18-O17 | Q18: -0.0030334725 | R18: =Q18*100 | S18: =R18-R17 | T18: =IF(OR(MID(A18,6,2)="02",MID(A18,6,2)="03"),1,0) | U18: =IF(T18=0,P18,"") | V18: =IF(T18=1,P18,"") | W18: =O18-O14 | X18: =IF(SUM(T15:T18)>0,1,0) | Y18: =IF(X18=0,W18,"") | Z18: =IF(X18=1,W18,"") | AA18: =IF(T18=0,S18,"") | AB18: =IF(T18=1,S18,"") | AC18: =R18-R14 | AD18: =IF(X18=0,AC18,"") | AE18: =IF(X18=1,AC18,"") | AF18: =H18-H14
A19: 2024-10-01 | B19: 384443.9 | C19: 510558.27 | D19: 424610.68 | E19: =IF(C19="","",B19/C19) | F19: =IF(E19="","",E19*100) | G19: =B19/D19 | H19: =G19*100 | I19: =IF(F19="","",H19-F19) | J19: =H19-H18 | K19: =(D19-D18)/D18*100 | L19: =(B19-B18)/B18*100 | M19: =IF(AND(K19<=por_sk,L19>=por_zaim),"оба",IF(K19<=por_sk,"СК",IF(L19>=por_zaim,"Займ",""))) | N19: -0.019642653 | O19: =N19*100 | P19: =O19-O18 | Q19: -0.003726465 | R19: =Q19*100 | S19: =R19-R18 | T19: =IF(OR(MID(A19,6,2)="02",MID(A19,6,2)="03"),1,0) | U19: =IF(T19=0,P19,"") | V19: =IF(T19=1,P19,"") | W19: =O19-O15 | X19: =IF(SUM(T16:T19)>0,1,0) | Y19: =IF(X19=0,W19,"") | Z19: =IF(X19=1,W19,"") | AA19: =IF(T19=0,S19,"") | AB19: =IF(T19=1,S19,"") | AC19: =R19-R15 | AD19: =IF(X19=0,AC19,"") | AE19: =IF(X19=1,AC19,"") | AF19: =H19-H15
A20: 2024-11-01 | B20: 376972.2 | C20: 525225.33 | D20: 439721.6 | E20: =IF(C20="","",B20/C20) | F20: =IF(E20="","",E20*100) | G20: =B20/D20 | H20: =G20*100 | I20: =IF(F20="","",H20-F20) | J20: =H20-H19 | K20: =(D20-D19)/D19*100 | L20: =(B20-B19)/B19*100 | M20: =IF(AND(K20<=por_sk,L20>=por_zaim),"оба",IF(K20<=por_sk,"СК",IF(L20>=por_zaim,"Займ",""))) | N20: -0.01965703 | O20: =N20*100 | P20: =O20-O19 | Q20: -0.0086988075 | R20: =Q20*100 | S20: =R20-R19 | T20: =IF(OR(MID(A20,6,2)="02",MID(A20,6,2)="03"),1,0) | U20: =IF(T20=0,P20,"") | V20: =IF(T20=1,P20,"") | W20: =O20-O16 | X20: =IF(SUM(T17:T20)>0,1,0) | Y20: =IF(X20=0,W20,"") | Z20: =IF(X20=1,W20,"") | AA20: =IF(T20=0,S20,"") | AB20: =IF(T20=1,S20,"") | AC20: =R20-R16 | AD20: =IF(X20=0,AC20,"") | AE20: =IF(X20=1,AC20,"") | AF20: =H20-H16
... A34: 2026-01-01 | B34: 421717.7 | C34: 503086.11 | D34: 439961.27 | E34: =IF(C34="","",B34/C34) | F34: =IF(E34="","",E34*100) | G34: =B34/D34 | H34: =G34*100 | I34: =IF(F34="","",H34-F34) | J34: =H34-H33 | K34: =(D34-D33)/D33*100 | L34: =(B34-B33)/B33*100 | M34: =IF(AND(K34<=por_sk,L34>=por_zaim),"оба",IF(K34<=por_sk,"СК",IF(L34>=por_zaim,"Займ",""))) | N34: -0.010006426 | O34: =N34*100 | P34: =O34-O33 | Q34: -0.009844636 | R34: =Q34*100 | S34: =R34-R33 | T34: =IF(OR(MID(A34,6,2)="02",MID(A34,6,2)="03"),1,0) | U34: =IF(T34=0,P34,"") | V34: =IF(T34=1,P34,"") | W34: =O34-O30 | X34: =IF(SUM(T31:T34)>0,1,0) | Y34: =IF(X34=0,W34,"") | Z34: =IF(X34=1,W34,"") | AA34: =IF(T34=0,S34,"") | AB34: =IF(T34=1,S34,"") | AC34: =R34-R30 | AD34: =IF(X34=0,AC34,"") | AE34: =IF(X34=1,AC34,"") | AF34: =H34-H30
A35: 2026-02-01 | B35: 393670.5 | D35: 440063.85 | E35: =IF(C35="","",B35/C35) | F35: =IF(E35="","",E35*100) | G35: =B35/D35 | H35: =G35*100 | I35: =IF(F35="","",H35-F35) | J35: =H35-H34 | K35: =(D35-D34)/D34*100 | L35: =(B35-B34)/B34*100 | M35: =IF(AND(K35<=por_sk,L35>=por_zaim),"оба",IF(K35<=por_sk,"СК",IF(L35>=por_zaim,"Займ",""))) | N35: 0.0062116289 | O35: =N35*100 | P35: =O35-O34 | Q35: 0.0047314406 | R35: =Q35*100 | S35: =R35-R34 | T35: =IF(OR(MID(A35,6,2)="02",MID(A35,6,2)="03"),1,0) | U35: =IF(T35=0,P35,"") | V35: =IF(T35=1,P35,"") | W35: =O35-O31 | X35: =IF(SUM(T32:T35)>0,1,0) | Y35: =IF(X35=0,W35,"") | Z35: =IF(X35=1,W35,"") | AA35: =IF(T35=0,S35,"") | AB35: =IF(T35=1,S35,"") | AC35: =R35-R31 | AD35: =IF(X35=0,AC35,"") | AE35: =IF(X35=1,AC35,"") | AF35: =H35-H31
A36: 2026-03-01 | B36: 395281.7 | D36: 449623.8 | E36: =IF(C36="","",B36/C36) | F36: =IF(E36="","",E36*100) | G36: =B36/D36 | H36: =G36*100 | I36: =IF(F36="","",H36-F36) | J36: =H36-H35 | K36: =(D36-D35)/D35*100 | L36: =(B36-B35)/B35*100 | M36: =IF(AND(K36<=por_sk,L36>=por_zaim),"оба",IF(K36<=por_sk,"СК",IF(L36>=por_zaim,"Займ",""))) | N36: 0.0011747746 | O36: =N36*100 | P36: =O36-O35 | Q36: 0.0029763559 | R36: =Q36*100 | S36: =R36-R35 | T36: =IF(OR(MID(A36,6,2)="02",MID(A36,6,2)="03"),1,0) | U36: =IF(T36=0,P36,"") | V36: =IF(T36=1,P36,"") | W36: =O36-O32 | X36: =IF(SUM(T33:T36)>0,1,0) | Y36: =IF(X36=0,W36,"") | Z36: =IF(X36=1,W36,"") | AA36: =IF(T36=0,S36,"") | AB36: =IF(T36=1,S36,"") | AC36: =R36-R32 | AD36: =IF(X36=0,AC36,"") | AE36: =IF(X36=1,AC36,"") | AF36: =H36-H32
A37: 2026-04-01 | B37: 416607.1 | D37: 446679.83 | E37: =IF(C37="","",B37/C37) | F37: =IF(E37="","",E37*100) | G37: =B37/D37 | H37: =G37*100 | I37: =IF(F37="","",H37-F37) | J37: =H37-H36 | K37: =(D37-D36)/D36*100 | L37: =(B37-B36)/B36*100 | M37: =IF(AND(K37<=por_sk,L37>=por_zaim),"оба",IF(K37<=por_sk,"СК",IF(L37>=por_zaim,"Займ",""))) | N37: -0.0034830032 | O37: =N37*100 | P37: =O37-O36 | Q37: 0.0019644136 | R37: =Q37*100 | S37: =R37-R36 | T37: =IF(OR(MID(A37,6,2)="02",MID(A37,6,2)="03"),1,0) | U37: =IF(T37=0,P37,"") | V37: =IF(T37=1,P37,"") | W37: =O37-O33 | X37: =IF(SUM(T34:T37)>0,1,0) | Y37: =IF(X37=0,W37,"") | Z37: =IF(X37=1,W37,"") | AA37: =IF(T37=0,S37,"") | AB37: =IF(T37=1,S37,"") | AC37: =R37-R33 | AD37: =IF(X37=0,AC37,"") | AE37: =IF(X37=1,AC37,"") | AF37: =H37-H33
A38: 2026-05-01 | B38: 439754.5 | D38: 446857.15 | E38: =IF(C38="","",B38/C38) | F38: =IF(E38="","",E38*100) | G38: =B38/D38 | H38: =G38*100 | I38: =IF(F38="","",H38-F38) | J38: =H38-H37 | K38: =(D38-D37)/D37*100 | L38: =(B38-B37)/B37*100 | M38: =IF(AND(K38<=por_sk,L38>=por_zaim),"оба",IF(K38<=por_sk,"СК",IF(L38>=por_zaim,"Займ",""))) | N38: -0.0033998343 | O38: =N38*100 | P38: =O38-O37 | Q38: 0.0019142856 | R38: =Q38*100 | S38: =R38-R37 | T38: =IF(OR(MID(A38,6,2)="02",MID(A38,6,2)="03"),1,0) | U38: =IF(T38=0,P38,"") | V38: =IF(T38=1,P38,"") | W38: =O38-O34 | X38: =IF(SUM(T35:T38)>0,1,0) | Y38: =IF(X38=0,W38,"") | Z38: =IF(X38=1,W38,"") | AA38: =IF(T38=0,S38,"") | AB38: =IF(T38=1,S38,"") | AC38: =R38-R34 | AD38: =IF(X38=0,AC38,"") | AE38: =IF(X38=1,AC38,"") | AF38: =H38-H34
A39: 2026-06-01 | B39: 444048.8 | D39: 440316.78 | E39: =IF(C39="","",B39/C39) | F39: =IF(E39="","",E39*100) | G39: =B39/D39 | H39: =G39*100 | I39: =IF(F39="","",H39-F39) | J39: =H39-H38 | K39: =(D39-D38)/D38*100 | L39: =(B39-B38)/B38*100 | M39: =IF(AND(K39<=por_sk,L39>=por_zaim),"оба",IF(K39<=por_sk,"СК",IF(L39>=por_zaim,"Займ",""))) | N39: 0.0037743682 | O39: =N39*100 | P39: =O39-O38 | Q39: 0.0033711825 | R39: =Q39*100 | S39: =R39-R38 | T39: =IF(OR(MID(A39,6,2)="02",MID(A39,6,2)="03"),1,0) | U39: =IF(T39=0,P39,"") | V39: =IF(T39=1,P39,"") | W39: =O39-O35 | X39: =IF(SUM(T36:T39)>0,1,0) | Y39: =IF(X39=0,W39,"") | Z39: =IF(X39=1,W39,"") | AA39: =IF(T39=0,S39,"") | AB39: =IF(T39=1,S39,"") | AC39: =R39-R35 | AD39: =IF(X39=0,AC39,"") | AE39: =IF(X39=1,AC39,"") | AF39: =H39-H35
A40: 2026-07-01 | B40: 448999.7 | D40: 442346.33 | E40: =IF(C40="","",B40/C40) | F40: =IF(E40="","",E40*100) | G40: =B40/D40 | H40: =G40*100 | I40: =IF(F40="","",H40-F40) | J40: =H40-H39 | K40: =(D40-D39)/D39*100 | L40: =(B40-B39)/B39*100 | M40: =IF(AND(K40<=por_sk,L40>=por_zaim),"оба",IF(K40<=por_sk,"СК",IF(L40>=por_zaim,"Займ",""))) | N40: -0.0026735176 | O40: =N40*100 | P40: =O40-O39 | Q40: 0.0026665901 | R40: =Q40*100 | S40: =R40-R39 | T40: =IF(OR(MID(A40,6,2)="02",MID(A40,6,2)="03"),1,0) | U40: =IF(T40=0,P40,"") | V40: =IF(T40=1,P40,"") | W40: =O40-O36 | X40: =IF(SUM(T37:T40)>0,1,0) | Y40: =IF(X40=0,W40,"") | Z40: =IF(X40=1,W40,"") | AA40: =IF(T40=0,S40,"") | AB40: =IF(T40=1,S40,"") | AC40: =R40-R36 | AD40: =IF(X40=0,AC40,"") | AE40: =IF(X40=1,AC40,"") | AF40: =H40-H36
A42: Колонки T–AE — режимное разделение по Г36: σ приращений CoR в феврале-марте впятеро выше, чем в остальные месяцы (5,04 по КБ/ПБ и 4,86 по МСБ против ≤ 1,76 у остальных десяти метрик). Отсюда эмпирические квантили считаются раздельно, и лист «Метрики» берёт границы зон отсюда. Колонка I — разрыв двух баз на одну дату, а не движение во времени. Через неё видно, что k не постоянен: разрыв сузился с 22,2 пп в 08.2023 до 12,0 пп в 01.2026. Уровень L = L_рег / k, посчитанный по k одной даты, стареет вместе с k — открытый вопрос к запросу данных, не свойство расчёта.
A44: Уровень не ограничивал показатель 8 лет 6 месяцев: шесть эпизодов превышения относительно уровня, действовавшего на дату.

Sheet Параметры
A1: Параметры расчёта
A2: Всё, что не выводится из ряда. Меняется здесь — пересчитывается везде.
A4: Параметр | B4: Обозначение | C4: Значение | D4: Формула | E4: Откуда
A5: Доверие для буфера | B5: p | C5: 0.9 | D5: ввод | E5: Доля T-месячных движений, которые буфер обязан накрыть. 0,90 означает один ложный отбой из десяти. Это РЕШЕНИЕ комитета о цене ложного сигнала, а не расчётная величина: выше p — жёлтая ниже, лампа горит чаще
A6: Квантиль нормального | B6: z(p) | C6: =NORMSINV(C5) | D6: NORMSINV(p) | E6: Вычисляется из p, не вбивается. По-русски функция называется НОРМСТОБР
A7: Отношение баз капитала | B7: k (Г26) | C7: =Ряд!D34/Ряд!C34 | D7: Ряд!D34/Ряд!C34 | E7: СК_балансовый / СК_регуляторный на 01.01.2026 — последняя дата, где есть обе базы. Находка Г26: с 01.01.2026 знаменатель метрики сменил базу, уровень при этом не пересматривался. ВНИМАНИЕ: k не константа, см. колонку I листа «Ряд»
A8: Уровень в регуляторной базе | B8: L_рег | C8: 95 | D8: ввод | E8: Действующий уровень риск-аппетита по топ-20. Приложение № 3 к Политике (VND-02). История уровня: 250 % → 95 %, см. data/top20_limit_history.csv
A9: Длина цикла реагирования, мес. | B9: T | C9: 3 | D9: ввод | E9: ДОПУЩЕНИЕ, не измеренная величина. Пока длина цикла не закреплена в регламенте, метод H держится на ней со слов — DISCLOSURE § 6
A10: Порог триггера по капиталу, % | B10: порог ΔСК | C10: -3 | D10: ввод | E10: Месячное падение СК, при котором наблюдение ускоряется независимо от зоны
A11: Порог триггера по портфелю, % | B11: порог ΔЗайм | C11: 5 | D11: ввод | E11: Месячный рост задолженности топ-20, при котором наблюдение ускоряется
A12: Уровень значимости проверки | B12: α | C12: 0.05 | D12: ввод | E12: Порог p-значения, ниже которого нормальность отвергается. 0,05 — обычай, а не норма: при α = 0,10 отсеялось бы больше метрик, при 0,01 — меньше. Проверка включена в расчёт с 15.09.2026 и определяет, каким методом размечается каждая метрика (развилка на листе «Как защищать»)
A13: Критическое A² Андерсона | B13: A²_крит | C13: 0.752 | D13: ввод | E13: Критическое значение статистики Андерсона-Дарлинга при α = 0,05 для неизвестных среднего и дисперсии. Таблица Стефенса (1974). В Excel сама статистика не считается — нужна сортировка ряда; внесена константой
A14: Порог решающей проверки | B14: τ | C14: 0.25 | D14: ввод | E14: Допустимое расхождение модельного квантиля z·σ·√T с фактическим. 0,25 — удвоенная собственная погрешность σ на 36 точках (±12 %): внутри этого коридора расхождение неразличимо от шума оценки самой σ. Формальная нормальность НЕ решает — решает эта величина
A16: Из десяти параметров вычисляются два: z из p и k из ряда. Остальные восемь — чьи-то решения, и у каждого должен быть автор. У L_рег он есть (Приложение № 3), у α и A²_крит — статистический обычай и таблица Стефенса; у T, τ и двух порогов триггеров — нет. T = 3 единственный без внешнего источника: поставьте другое число в C9 — вся книга пересчитается, и станет видно, что требуемый уровень меняется на 1,4–1,5 пп за каждый месяц цикла.

Sheet Метрики — ряд
A1: Месячный ряд розничных метрик: 36 точек, 01.08.2023 — 01.07.2026
A2: Колонки 4м1…4м32 — изменения за четыре месяца: вход эмпирического квантиля и триггера T2. Источник: лист Monthly книги Приложения № 3 к Политике, получен 04.09.2026. Значения в процентах — в исходном листе они долями. Сверено с квартальной формой № 50 на 01.07.2026: максимальное расхождение 0,0009 пп. ОГОВОРКА (DECOMPOSITION § 10.2): из 36 месяцев с отчётностью сверены 20, первые 16 — реконструкция, величин уполномоченный орган не видел.
A4: Метрика | B4: Сегмент | C4: Лимит L | D4: 2023-08 | E4: 2023-09 | F4: 2023-10 | G4: 2023-11 | H4: 2023-12 | I4: 2024-01 | J4: 2024-02 | K4: 2024-03 | L4: 2024-04 | M4: 2024-05 | N4: 2024-06 | O4: 2024-07 | P4: 2024-08 | Q4: 2024-09 | R4: 2024-10 | S4: 2024-11 | T4: 2024-12 | U4: 2025-01 | V4: 2025-02 | W4: 2025-03 | X4: 2025-04 | Y4: 2025-05 | Z4: 2025-06 | AA4: 2025-07 | AB4: 2025-08 | AC4: 2025-09 | AD4: 2025-10 | AE4: 2025-11 | AF4: 2025-12 | AG4: 2026-01 | AH4: 2026-02 | AI4: 2026-03 | AJ4: 2026-04 | AK4: 2026-05 | AL4: 2026-06 | AM4: 2026-07 | AO4: Δ1 | AP4: Δ2 | AQ4: Δ3 | AR4: Δ4 | AS4: Δ5 | AT4: Δ6 | AU4: Δ7 | AV4: Δ8 | AW4: Δ9 | AX4: Δ10 | AY4: Δ11 | AZ4: Δ12 | BA4: Δ13 | BB4: Δ14 | BC4: Δ15 | BD4: Δ16 | BE4: Δ17 | BF4: Δ18 | BG4: Δ19 | BH4: Δ20 | BI4: Δ21 | BJ4: Δ22 | BK4: Δ23 | BL4: Δ24 | BM4: Δ25 | BN4: Δ26 | BO4: Δ27 | BP4: Δ28 | BQ4: Δ29 | BR4: Δ30 | BS4: Δ31 | BT4: Δ32 | BU4: Δ33 | BV4: Δ34 | BW4: Δ35 | BY4: 4м1 | BZ4: 4м2 | CA4: 4м3 | CB4: 4м4 | CC4: 4м5 | CD4: 4м6 | CE4: 4м7 | CF4: 4м8 | CG4: 4м9 | CH4: 4м10 | CI4: 4м11 | CJ4: 4м12 | CK4: 4м13 | CL4: 4м14 | CM4: 4м15 | CN4: 4м16 | CO4: 4м17 | CP4: 4м18 | CQ4: 4м19 | CR4: 4м20 | CS4: 4м21 | CT4: 4м22 | CU4: 4м23 | CV4: 4м24 | CW4: 4м25 | CX4: 4м26 | CY4: 4м27 | CZ4: 4м28 | DA4: 4м29 | DB4: 4м30 | DC4: 4м31 | DD4: 4м32
A5: EL — ожидаемые потери, всего | B5: RB | C5: 9 | D5: 4.01893 | E5: 4.006073 | F5: 3.918858 | G5: 3.916775 | H5: 3.902911 | I5: 3.860625 | J5: 3.783252 | K5: 3.753594 | L5: 3.705587 | M5: 3.746765 | N5: 3.861943 | O5: 3.763018 | P5: 3.619708 | Q5: 3.587173 | R5: 3.411962 | S5: 3.067174 | T5: 3.066544 | U5: 3.032757 | V5: 2.944715 | W5: 2.92572 | X5: 2.918222 | Y5: 2.896367 | Z5: 2.896783 | AA5: 2.784058 | AB5: 2.763943 | AC5: 2.682605 | AD5: 2.634274 | AE5: 2.58102 | AF5: 2.536831 | AG5: 2.615049 | AH5: 2.616212 | AI5: 2.671571 | AJ5: 2.713037 | AK5: 2.711398 | AL5: 2.718967 | AM5: 2.757284 | AO5: =E5-D5 | AP5: =F5-E5 | AQ5: =G5-F5 | AR5: =H5-G5 | AS5: =I5-H5 | AT5: =J5-I5 | AU5: =K5-J5 | AV5: =L5-K5 | ... BW5: =AM5-AL5 | BY5: =H5-D5 | BZ5: =I5-E5 | CA5: =J5-F5 | CB5: =K5-G5 | CC5: =L5-H5 | CD5: =M5-I5 | CE5: =N5-J5 | CF5: =O5-K5 | ... DD5: =AM5-AI5
A6: EL — необеспеченные | B6: RB | C6: 10 | D6: 7.423354 | E6: 7.500904 | F6: 7.404206 | G6: 7.442255 | H6: 7.630703 | I6: 7.607814 | J6: 7.565199 | K6: 7.556539 | L6: 7.545619 | M6: 7.541218 | N6: 7.699862 | O6: 7.656452 | P6: 7.489877 | Q6: 7.385384 | R6: 7.223349 | S6: 6.880542 | T6: 7.034851 | U6: 7.219599 | V6: 7.049311 | W6: 7.13935 | X6: 7.081359 | Y6: 7.078887 | Z6: 7.126308 | AA6: 7.074532 | AB6: 7.164825 | AC6: 7.147442 | AD6: 7.099976 | AE6: 7.092606 | AF6: 7.069679 | AG6: 7.031319 | AH6: 7.029701 | AI6: 7.028161 | AJ6: 7.011424 | AK6: 7.3706 | AL6: 7.377971 | AM6: 7.566672 | AO6: =E6-D6 | AP6: =F6-E6 | AQ6: =G6-F6 | AR6: =H6-G6 | AS6: =I6-H6 | AT6: =J6-I6 | AU6: =K6-J6 | AV6: =L6-K6 | ... BW6: =AM6-AL6 | BY6: =H6-D6 | BZ6: =I6-E6 | CA6: =J6-F6 | CB6: =K6-G6 | CC6: =L6-H6 | CD6: =M6-I6 | CE6: =N6-J6 | CF6: =O6-K6 | ... DD6: =AM6-AI6
A7: EL — обеспеченные | B7: RB | C7: 7 | D7: 1.334152 | E7: 1.334097 | F7: 1.324876 | G7: 1.363572 | H7: 1.347993 | I7: 1.424419 | J7: 1.395834 | K7: 1.412628 | L7: 1.416922 | M7: 1.481267 | N7: 1.570876 | O7: 1.497854 | P7: 1.435108 | Q7: 1.443728 | R7: 1.338809 | S7: 1.235632 | T7: 1.311974 | U7: 1.327887 | V7: 1.315344 | W7: 1.32047 | X7: 1.365542 | Y7: 1.381124 | Z7: 1.397907 | AA7: 1.370362 | AB7: 1.3795 | AC7: 1.349421 | AD7: 1.348437 | AE7: 1.322858 | AF7: 1.308495 | AG7: 1.427522 | AH7: 1.449854 | AI7: 1.528519 | AJ7: 1.589895 | AK7: 1.552727 | AL7: 1.606792 | AM7: 1.635852 | AO7: =E7-D7 | AP7: =F7-E7 | AQ7: =G7-F7 | AR7: =H7-G7 | AS7: =I7-H7 | AT7: =J7-I7 | AU7: =K7-J7 | AV7: =L7-K7 | ... BW7: =AM7-AL7 | BY7: =H7-D7 | BZ7: =I7-E7 | CA7: =J7-F7 | CB7: =K7-G7 | CC7: =L7-H7 | CD7: =M7-I7 | CE7: =N7-J7 | CF7: =O7-K7 | ... DD7: =AM7-AI7
A8: EL — прочие | B8: RB | C8: 10 | D8: 3.326879 | E8: 3.202222 | F8: 3.1625 | G8: 3.149127 | H8: 3.160358 | I8: 3.051504 | J8: 3.056607 | K8: 3.012888 | L8: 3.014183 | M8: 2.959452 | N8: 3.013192 | O8: 3.064589 | P8: 2.827206 | Q8: 2.773865 | R8: 2.754806 | S8: 2.752117 | T8: 2.65327 | U8: 2.565213 | V8: 2.612028 | W8: 2.654717 | X8: 2.738199 | Y8: 2.571633 | Z8: 2.445707 | AA8: 2.403899 | AB8: 2.404753 | AC8: 2.376893 | AD8: 2.546951 | AE8: 2.561576 | AF8: 2.542604 | AG8: 2.455625 | AH8: 2.303325 | AI8: 2.321167 | AJ8: 2.289344 | AK8: 2.348211 | AL8: 2.306177 | AM8: 2.471786 | AO8: =E8-D8 | AP8: =F8-E8 | AQ8: =G8-F8 | AR8: =H8-G8 | AS8: =I8-H8 | AT8: =J8-I8 | AU8: =K8-J8 | AV8: =L8-K8 | ... BW8: =AM8-AL8 | BY8: =H8-D8 | BZ8: =I8-E8 | CA8: =J8-F8 | CB8: =K8-G8 | CC8: =L8-H8 | CD8: =M8-I8 | CE8: =N8-J8 | CF8: =O8-K8 | ... DD8: =AM8-AI8
A9: PD — необеспеченные | B9: RB | C9: 15 | D9: 11.60745 | E9: 11.60097 | F9: 11.557592 | G9: 11.600434 | H9: 11.609779 | I9: 11.578222 | J9: 11.504748 | K9: 11.470526 | L9: 11.567866 | M9: 11.537957 | N9: 11.689138 | O9: 11.74201 | P9: 11.687766 | Q9: 11.716373 | R9: 11.627811 | S9: 11.221708 | T9: 11.558577 | U9: 11.760264 | V9: 11.559204 | W9: 11.592315 | X9: 11.533197 | Y9: 11.505819 | Z9: 11.613521 | AA9: 11.503023 | AB9: 11.624704 | AC9: 11.571404 | AD9: 11.538188 | AE9: 11.503777 | AF9: 11.398796 | AG9: 11.227537 | AH9: 11.207139 | AI9: 11.177429 | AJ9: 11.041782 | AK9: 11.006035 | AL9: 10.98054 | AM9: 10.961171 | AO9: =E9-D9 | AP9: =F9-E9 | AQ9: =G9-F9 | AR9: =H9-G9 | AS9: =I9-H9 | AT9: =J9-I9 | AU9: =K9-J9 | AV9: =L9-K9 | ... BW9: =AM9-AL9 | BY9: =H9-D9 | BZ9: =I9-E9 | CA9: =J9-F9 | CB9: =K9-G9 | CC9: =L9-H9 | CD9: =M9-I9 | CE9: =N9-J9 | CF9: =O9-K9 | ... DD9: =AM9-AI9
A10: PD — необеспеченные, наличные | B10: RB | C10: 15 | D10: 11.674808 | E10: 11.668178 | F10: 11.61045 | G10: 11.661356 | H10: 11.655618 | I10: 11.614657 | J10: 11.584871 | K10: 11.584976 | L10: 11.69753 | M10: 11.659563 | N10: 11.865741 | O10: 11.917347 | P10: 11.843573 | Q10: 11.888088 | R10: 11.812672 | S10: 11.320271 | T10: 11.711669 | U10: 11.95958 | V10: 11.735592 | W10: 11.762706 | X10: 11.704674 | Y10: 11.675266 | Z10: 11.795348 | AA10: 11.668777 | AB10: 11.789555 | AC10: 11.726212 | AD10: 11.70914 | AE10: 11.651701 | AF10: 11.531915 | AG10: 11.341787 | AH10: 11.319256 | AI10: 11.279728 | AJ10: 11.12813 | AK10: 11.092788 | AL10: 11.065915 | AM10: 11.046123 | AO10: =E10-D10 | AP10: =F10-E10 | AQ10: =G10-F10 | AR10: =H10-G10 | AS10: =I10-H10 | AT10: =J10-I10 | AU10: =K10-J10 | AV10: =L10-K10 | ... BW10: =AM10-AL10 | BY10: =H10-D10 | BZ10: =I10-E10 | CA10: =J10-F10 | CB10: =K10-G10 | CC10: =L10-H10 | CD10: =M10-I10 | CE10: =N10-J10 | CF10: =O10-K10 | ... DD10: =AM10-AI10
A11: PD — необеспеченные, товарные | B11: RB | C11: 15 | D11: 11.50521 | E11: 11.50766 | F11: 11.54243 | G11: 11.55294 | H11: 11.651115 | I11: 11.668182 | J11: 11.352983 | K11: 11.106068 | L11: 11.114965 | M11: 11.141404 | N11: 10.962641 | O11: 11.007145 | P11: 11.075746 | Q11: 11.00069 | R11: 10.821536 | S11: 10.931785 | T11: 10.944521 | U11: 10.843042 | V11: 10.762585 | W11: 10.804766 | X11: 10.735113 | Y11: 10.688897 | Z11: 10.682042 | AA11: 10.659418 | AB11: 10.766198 | AC11: 10.756449 | AD11: 10.534971 | AE11: 10.655369 | AF11: 10.633609 | AG11: 10.600999 | AH11: 10.577046 | AI11: 10.597294 | AJ11: 10.629639 | AK11: 10.577601 | AL11: 10.612922 | AM11: 10.586523 | AO11: =E11-D11 | AP11: =F11-E11 | AQ11: =G11-F11 | AR11: =H11-G11 | AS11: =I11-H11 | AT11: =J11-I11 | AU11: =K11-J11 | AV11: =L11-K11 | ... BW11: =AM11-AL11 | BY11: =H11-D11 | BZ11: =I11-E11 | CA11: =J11-F11 | CB11: =K11-G11 | CC11: =L11-H11 | CD11: =M11-I11 | CE11: =N11-J11 | CF11: =O11-K11 | ... DD11: =AM11-AI11
A12: PD — обеспеченные | B12: RB | C12: 7 | D12: 4.686167 | E12: 4.757833 | F12: 4.71486 | G12: 4.769401 | H12: 4.703394 | I12: 4.713498 | J12: 4.709291 | K12: 4.765951 | L12: 4.872496 | M12: 4.872588 | N12: 5.174162 | O12: 5.1579 | P12: 5.192143 | Q12: 5.284508 | R12: 5.078941 | S12: 4.80978 | T12: 5.05383 | U12: 5.056691 | V12: 5.062908 | W12: 5.10031 | X12: 5.158827 | Y12: 5.188293 | Z12: 5.265188 | AA12: 5.145208 | AB12: 5.170206 | AC12: 5.180577 | AD12: 5.147123 | AE12: 5.141497 | AF12: 5.07536 | AG12: 5.087058 | AH12: 5.094358 | AI12: 5.105313 | AJ12: 5.097632 | AK12: 5.027749 | AL12: 5.033045 | AM12: 5.014115 | AO12: =E12-D12 | AP12: =F12-E12 | AQ12: =G12-F12 | AR12: =H12-G12 | AS12: =I12-H12 | AT12: =J12-I12 | AU12: =K12-J12 | AV12: =L12-K12 | ... BW12: =AM12-AL12 | BY12: =H12-D12 | BZ12: =I12-E12 | CA12: =J12-F12 | CB12: =K12-G12 | CC12: =L12-H12 | CD12: =M12-I12 | CE12: =N12-J12 | CF12: =O12-K12 | ... DD12: =AM12-AI12
A13: PD — прочие | B13: RB | C13: 14 | D13: 5.170665 | E13: 4.970544 | F13: 4.914703 | G13: 4.891764 | H13: 4.888883 | I13: 4.727811 | J13: 4.681111 | K13: 4.61092 | L13: 4.614513 | M13: 4.586092 | N13: 4.54441 | O13: 4.62125 | P13: 4.498773 | Q13: 4.443795 | R13: 4.469202 | S13: 4.463136 | T13: 4.299537 | U13: 4.234974 | V13: 4.355903 | W13: 4.396757 | X13: 4.471538 | Y13: 4.195269 | Z13: 4.12505 | AA13: 4.047016 | AB13: 4.042882 | AC13: 3.989124 | AD13: 4.268485 | AE13: 4.285341 | AF13: 4.248105 | AG13: 4.089569 | AH13: 3.828689 | AI13: 3.845012 | AJ13: 3.778529 | AK13: 3.723774 | AL13: 3.646836 | AM13: 3.654987 | AO13: =E13-D13 | AP13: =F13-E13 | AQ13: =G13-F13 | AR13: =H13-G13 | AS13: =I13-H13 | AT13: =J13-I13 | AU13: =K13-J13 | AV13: =L13-K13 | ... BW13: =AM13-AL13 | BY13: =H13-D13 | BZ13: =I13-E13 | CA13: =J13-F13 | CB13: =K13-G13 | CC13: =L13-H13 | CD13: =M13-I13 | CE13: =N13-J13 | CF13: =O13-K13 | ... DD13: =AM13-AI13

Sheet Расчёт
A1: Расчётный лист: формула, вход, результат
A2: Колонка D считается формулой из листов «Ряд» и «Параметры». Колонка E — то, что напечатано в DECOMPOSITION § 11.10 и DISCLOSURE § 2. Колонка G должна быть «да» во всех строках: иначе опубликованное число разошлось с расчётом.
A4: Показатель | B4: Формула словами | C4: Формула в этой книге | D4: Значение | E4: Где напечатано
A5: 1. База: что даёт сам ряд
A6: σ_Δ — с.к.о. месячных приростов | B6: выборочное с.к.о. (n−1) по всем 35 приростам | C6: STDEV(d) | D6: =STDEV(d) | E6: DISCLOSURE § 2.1
A7: σ уровней (метод М1) | B7: выборочное с.к.о. самих значений ряда, не приростов | C7: STDEV(v) | D7: =STDEV(v) | E7: DISCLOSURE Р-Д1
A8: Текущая точка, 01.07.2026 | B8: последнее значение ряда | C8: Ряд!H40 | D8: =Ряд!H40 | E8: DISCLOSURE § 2.1
A9: Максимум ряда, 01.2024 | B9: наибольшее значение ряда | C9: MAX(v) | D9: =MAX(v) | E9: DISCLOSURE § 2.1
A10: Число точек | B10: сколько наблюдений в ряде | C10: COUNT(v) | D10: =COUNT(v) | E10: DISCLOSURE § 1
A11: 2. Уровень
A12: L — уровень в балансовой базе | B12: действующий уровень 95 %, пересчитанный под балансовый капитал: L_рег / k | C12: L_reg/k_G26 | D12: =L_reg/k_G26 | E12: DISCLOSURE § 2.2
A13: X — граница L − M(3) в процентах лимита | B13: 1 − M(T)/L: доля лимита, на которой стоит жёлтая линия | C13: (1-D24/D12)*100 | D13: =(1-D24/D12)*100 | E13: новое, 14.09.2026
A14: Это одна величина в двух системах измерения, а не два разных лимита. Фраза «пробит лимит 95 % по балансовому капиталу» — категориальная ошибка: числитель берётся из одной базы, знаменатель из другой. Значение 108,6304 стоит на k, посчитанном из ряда; в DISCLOSURE до 14.09.2026 печаталось 108,6298 — та же величина при k, округлённом до пяти знаков.
A15: 3. Запас на реагирование M(T) = z(p) · σ_Δ · √T и границы L − M(T)
A16: Запас M(T) при T = 1 | B16: z(p) × σ_Δ × корень из T | C16: z_p*D6*SQRT(1) | D16: =z_p*D6*SQRT(1) | E16: DISCLOSURE § 2.3
A17: Граница L − M(T) при T = 1 | B17: L − M(T) | C17: D12-D16 | D17: =D12-D16 | E17: DISCLOSURE § 2.3
A18: Наблюдений выше границы, T = 1 | B18: сколько точек ряда не ниже этой границы | C18: COUNTIF(v,">="&D17) | D18: =COUNTIF(v,">="&D17) | E18: DISCLOSURE § 2.3, Р-Д3
A19: Доля времени выше границы, T = 1 | B19: их доля от 36 наблюдений | C19: COUNTIF(v,">="&D17)/COUNT(v)*100 | D19: =COUNTIF(v,">="&D17)/COUNT(v)*100 | E19: DISCLOSURE § 2.3, Р-Д3
A20: Запас M(T) при T = 2 | B20: z(p) × σ_Δ × корень из T | C20: z_p*D6*SQRT(2) | D20: =z_p*D6*SQRT(2) | E20: DISCLOSURE § 2.3
A21: Граница L − M(T) при T = 2 | B21: L − M(T) | C21: D12-D20 | D21: =D12-D20 | E21: DISCLOSURE § 2.3
A22: Наблюдений выше границы, T = 2 | B22: сколько точек ряда не ниже этой границы | C22: COUNTIF(v,">="&D21) | D22: =COUNTIF(v,">="&D21) | E22: DISCLOSURE § 2.3, Р-Д3
A23: Доля времени выше границы, T = 2 | B23: их доля от 36 наблюдений | C23: COUNTIF(v,">="&D21)/COUNT(v)*100 | D23: =COUNTIF(v,">="&D21)/COUNT(v)*100 | E23: DISCLOSURE § 2.3, Р-Д3
A24: Запас M(T) при T = 3 | B24: z(p) × σ_Δ × корень из T | C24: z_p*D6*SQRT(3) | D24: =z_p*D6*SQRT(3) | E24: DISCLOSURE § 2.3
A25: Граница L − M(T) при T = 3 | B25: L − M(T) | C25: D12-D24 | D25: =D12-D24 | E25: DISCLOSURE § 2.3
A26: Наблюдений выше границы, T = 3 | B26: сколько точек ряда не ниже этой границы | C26: COUNTIF(v,">="&D25) | D26: =COUNTIF(v,">="&D25) | E26: DISCLOSURE § 2.3, Р-Д3
A27: Доля времени выше границы, T = 3 | B27: их доля от 36 наблюдений | C27: COUNTIF(v,">="&D25)/COUNT(v)*100 | D27: =COUNTIF(v,">="&D25)/COUNT(v)*100 | E27: DISCLOSURE § 2.3, Р-Д3
A28: Запас M(T) при T = 4 | B28: z(p) × σ_Δ × корень из T | C28: z_p*D6*SQRT(4) | D28: =z_p*D6*SQRT(4) | E28: DISCLOSURE § 2.3
A29: Граница L − M(T) при T = 4 | B29: L − M(T) | C29: D12-D28 | D29: =D12-D28 | E29: DISCLOSURE § 2.3
A30: Наблюдений выше границы, T = 4 | B30: сколько точек ряда не ниже этой границы | C30: COUNTIF(v,">="&D29) | D30: =COUNTIF(v,">="&D29) | E30: DISCLOSURE § 2.3, Р-Д3
A31: Доля времени выше границы, T = 4 | B31: их доля от 36 наблюдений | C31: COUNTIF(v,">="&D29)/COUNT(v)*100 | D31: =COUNTIF(v,">="&D29)/COUNT(v)*100 | E31: DISCLOSURE § 2.3, Р-Д3
A32: Р-Д3: доля в процентах от 36 наблюдений читается точнее, чем есть. 2,8 % — это одно наблюдение, 11,1 % — четыре. На комитете доля называется только вместе с числом наблюдений, поэтому строка «Наблюдений» стоит выше строки «Доля», а не под ней. Обоснование самой формулы M(T) — на листе «Обоснование M(T)»; разметка зон по этим границам — на листе «Зоны».
A33: 4. Квантили ряда (метод C). Линейная интерполяция между порядковыми статистиками
A34: Квантиль 85 % | B34: значение, ниже которого лежит 85 % ряда | C34: PERCENTILE(v,0.85) | D34: =PERCENTILE(v,0.85) | E34: DISCLOSURE § 2.5
A35: Квантиль 90 % | B35: значение, ниже которого лежит 90 % ряда | C35: PERCENTILE(v,0.90) | D35: =PERCENTILE(v,0.90) | E35: DISCLOSURE § 2.5
A36: Квантиль 95 % | B36: значение, ниже которого лежит 95 % ряда | C36: PERCENTILE(v,0.95) | D36: =PERCENTILE(v,0.95) | E36: DISCLOSURE § 2.5
A37: 5. Два независимых пути к одному уровню
A38: Метод H: квантиль 90 % + запас T = 3 | B38: квантиль₉₀(v) + M(3) | C38: D35+D24 | D38: =D35+D24 | E38: DISCLOSURE § 2.4
A39: Расхождение двух путей | B39: L (пересчёт базы) − H (цикл решения) | C39: D12-D38 | D39: =D12-D38 | E39: DISCLOSURE § 2.4
A40: Главный довод против упрёка «уровень подогнан под факт»: пути не связаны по построению. Первый смотрит на отношение баз капитала, второй — на распределение ряда и длину процесса. Сходятся на 0,05 пп.
A41: 6. Производные метрики
A42: D — расстояние до L, в σ | B42: (L − текущая точка) / σ_Δ | C42: (D12-D8)/D6 | D42: =(D12-D8)/D6 | E42: DISCLOSURE § 2.6
A43: D при сохранении L = 95 | B43: (95 − текущая точка) / σ_Δ | C43: (L_reg-D8)/D6 | D43: =(L_reg-D8)/D6 | E43: DISCLOSURE § 2.6
A44: F — падение СК до достижения L, % | B44: текущая точка / L − 1, в процентах | C44: (D8/D12-1)*100 | D44: =(D8/D12-1)*100 | E44: DISCLOSURE § 2.6
A45: T* — остаток времени до лимита, мес. | B45: сколько месяцев до лимита при доверии p: ((L − v) / (z·σ_Δ))² | C45: ((D12-D8)/(z_p*D6))^2 | D45: =((D12-D8)/(z_p*D6))^2 | E45: новое, 14.09.2026
A46: T* — та же формула M(T), решённая относительно T. Она переводит зону из цвета в срок: в текущей точке до лимита остаётся 1,87 месяца при доверии 90 %. Это число говорит комитету больше, чем «мы в жёлтой зоне».
A47: 7. Цена решения «уровень не трогаем»: обратный счёт при L = 95
A48: Жёлтая линия при L = 95 | B48: 95 − M(3) | C48: L_reg-D24 | D48: =L_reg-D24 | E48: DISCLOSURE § 2.6
A49: Наблюдений выше неё | B49: сколько точек ряда не ниже 85,97 | C49: COUNTIF(v,">="&D48) | D49: =COUNTIF(v,">="&D48) | E49: DISCLOSURE § 2.6
A50: Доля времени выше неё | B50: их доля от 36 наблюдений | C50: COUNTIF(v,">="&D48)/COUNT(v)*100 | D50: =COUNTIF(v,">="&D48)/COUNT(v)*100 | E50: DISCLOSURE § 2.6
A51: 31 наблюдение из 36 — это светофор с постоянно горящей жёлтой лампой. Именно это число отвечает на предложение «оставить 95 % и ничего не менять».
A52: 8. Проверка нормальности: какая метрика каким методом размечается
A53: Проверка встроена в расчёт, а не вынесена отдельно: от неё зависит, какой формулой считается зона каждой из двенадцати метрик. Развилка описана на листе «Как защищать», её параметры (α, A²_крит, τ) — на «Параметры». Таблица ниже — короткий расчёт по каждой метрике; полные границы зон и их применение — на листе «Метрики».
A55: Метрика | B55: Ряд приращений | C55: Вердикт формальный | D55: Жарк-Бера | E55: Что это значит для метода | F55: Асим. | G55: Экс. | H55: p(ЖБ) | I55: Шапиро p ⚠ | J55: Андерсон ⚠ | K55: M(4) модель | L55: Q90(4м) факт | M55: Расх., % | N55: МЕТОД | P55: n | Q55: среднее | R55: m₂ | S55: m₃ | T55: m₄
A56: Топ-20 / СК | B56: Ряд!J6:J40 | C56: =IF(AND(H56>alpha,I56>alpha,J56<ad_crit),"нормально","НЕ нормально") | D56: =P56/6*(F56^2+(G56-3)^2/4) | E56: Единственная метрика, проходящая все три критерия и решающую проверку. M(T) применяется без оговорок | F56: =S56/R56^1.5 | G56: =T56/R56^2 | H56: =CHIDIST(D56,2) | I56: 0.1099848 | J56: 0.62045554 | K56: =z_p*STDEV('Ряд'!J6:J40)*SQRT(4) | L56: =PERCENTILE('Ряд'!AF9:AF40,p_conf) | M56: =(K56-L56)/ABS(L56)*100 | N56: =IF(K56>=O56,"ЗАМЕНА: вырожден",IF(ABS(M56)<=tau*100,"M(T) — совпадает",IF(M56<0,"ЗАМЕНА: занижает","M(T) — консервативна"))) | O56: ='Метрики'!C5 | P56: =COUNT('Ряд'!J6:J40) | Q56: =AVERAGE('Ряд'!J6:J40) | R56: =SUMPRODUCT(('Ряд'!J6:J40-Q56)^2)/P56 | S56: =SUMPRODUCT(('Ряд'!J6:J40-Q56)^3)/P56 | T56: =SUMPRODUCT(('Ряд'!J6:J40-Q56)^4)/P56
A57: CoR КБ/ПБ | B57: Ряд!P6:P40 | C57: =IF(AND(H57>alpha,I57>alpha,J57<ad_crit),"нормально","НЕ нормально") | D57: =P57/6*(F57^2+(G57-3)^2/4) | E57: Буфер M(4) = 3,2850 больше самого лимита 3,00 — зона вырождается. Замена: эмпирический квантиль с режимным разделением (Г36) | F57: =S57/R57^1.5 | G57: =T57/R57^2 | H57: =CHIDIST(D57,2) | I57: 4.009734e-06 | J57: 2.3835894 | K57: =z_p*STDEV('Ряд'!P6:P40)*SQRT(4) | L57: =PERCENTILE('Ряд'!W9:W40,p_conf) | M57: =(K57-L57)/ABS(L57)*100 | N57: =IF(K57>=O57,"ЗАМЕНА: вырожден",IF(ABS(M57)<=tau*100,"M(T) — совпадает",IF(M57<0,"ЗАМЕНА: занижает","M(T) — консервативна"))) | O57: ='Метрики'!C6 | P57: =COUNT('Ряд'!P6:P40) | Q57: =AVERAGE('Ряд'!P6:P40) | R57: =SUMPRODUCT(('Ряд'!P6:P40-Q57)^2)/P57 | S57: =SUMPRODUCT(('Ряд'!P6:P40-Q57)^3)/P57 | T57: =SUMPRODUCT(('Ряд'!P6:P40-Q57)^4)/P57
A58: CoR МСБ | B58: Ряд!S6:S40 | C58: =IF(AND(H58>alpha,I58>alpha,J58<ad_crit),"нормально","НЕ нормально") | D58: =P58/6*(F58^2+(G58-3)^2/4) | E58: Завышение 28 %, чуть выше порога. Размечена тем же методом, что и КБ/ПБ, ради сопоставимости внутри пары | F58: =S58/R58^1.5 | G58: =T58/R58^2 | H58: =CHIDIST(D58,2) | I58: 0.0002083049 | J58: 1.7661296 | K58: =z_p*STDEV('Ряд'!S6:S40)*SQRT(4) | L58: =PERCENTILE('Ряд'!AC9:AC40,p_conf) | M58: =(K58-L58)/ABS(L58)*100 | N58: =IF(K58>=O58,"ЗАМЕНА: вырожден",IF(ABS(M58)<=tau*100,"M(T) — совпадает",IF(M58<0,"ЗАМЕНА: занижает","M(T) — консервативна"))) | O58: ='Метрики'!C8 | P58: =COUNT('Ряд'!S6:S40) | Q58: =AVERAGE('Ряд'!S6:S40) | R58: =SUMPRODUCT(('Ряд'!S6:S40-Q58)^2)/P58 | S58: =SUMPRODUCT(('Ряд'!S6:S40-Q58)^3)/P58 | T58: =SUMPRODUCT(('Ряд'!S6:S40-Q58)^4)/P58
A59: EL — всего | B59: Метрики — ряд!AO5:BW5 | C59: =IF(AND(H59>alpha,I59>alpha,J59<ad_crit),"нормально","НЕ нормально") | D59: =P59/6*(F59^2+(G59-3)^2/4) | E59: Завышение 128 % — снос, а не хвосты: метрика падает три года, а M(T) считает снос нулевым. Завышение безопасно | F59: =S59/R59^1.5 | G59: =T59/R59^2 | H59: =CHIDIST(D59,2) | I59: 0.0011683988 | J59: 1.0756103 | K59: =z_p*STDEV('Метрики — ряд'!AO5:BW5)*SQRT(4) | L59: =PERCENTILE('Метрики — ряд'!BY5:DD5,p_conf) | M59: =(K59-L59)/ABS(L59)*100 | N59: =IF(K59>=O59,"ЗАМЕНА: вырожден",IF(ABS(M59)<=tau*100,"M(T) — совпадает",IF(M59<0,"ЗАМЕНА: занижает","M(T) — консервативна"))) | O59: ='Метрики'!C10 | P59: =COUNT('Метрики — ряд'!AO5:BW5) | Q59: =AVERAGE('Метрики — ряд'!AO5:BW5) | R59: =SUMPRODUCT(('Метрики — ряд'!AO5:BW5-Q59)^2)/P59 | S59: =SUMPRODUCT(('Метрики — ряд'!AO5:BW5-Q59)^3)/P59 | T59: =SUMPRODUCT(('Метрики — ряд'!AO5:BW5-Q59)^4)/P59
A60: EL — необеспеченные | B60: Метрики — ряд!AO6:BW6 | C60: =IF(AND(H60>alpha,I60>alpha,J60<ad_crit),"нормально","НЕ нормально") | D60: =P60/6*(F60^2+(G60-3)^2/4) | E60: Завышение 28 %, на границе порога. Остаётся на M(T) | F60: =S60/R60^1.5 | G60: =T60/R60^2 | H60: =CHIDIST(D60,2) | I60: 0.062193856 | J60: 0.95527799 | K60: =z_p*STDEV('Метрики — ряд'!AO6:BW6)*SQRT(4) | L60: =PERCENTILE('Метрики — ряд'!BY6:DD6,p_conf) | M60: =(K60-L60)/ABS(L60)*100 | N60: =IF(K60>=O60,"ЗАМЕНА: вырожден",IF(ABS(M60)<=tau*100,"M(T) — совпадает",IF(M60<0,"ЗАМЕНА: занижает","M(T) — консервативна"))) | O60: ='Метрики'!C11 | P60: =COUNT('Метрики — ряд'!AO6:BW6) | Q60: =AVERAGE('Метрики — ряд'!AO6:BW6) | R60: =SUMPRODUCT(('Метрики — ряд'!AO6:BW6-Q60)^2)/P60 | S60: =SUMPRODUCT(('Метрики — ряд'!AO6:BW6-Q60)^3)/P60 | T60: =SUMPRODUCT(('Метрики — ряд'!AO6:BW6-Q60)^4)/P60
A61: EL — обеспеченные | B61: Метрики — ряд!AO7:BW7 | C61: =IF(AND(H61>alpha,I61>alpha,J61<ad_crit),"нормально","НЕ нормально") | D61: =P61/6*(F61^2+(G61-3)^2/4) | E61: Проходит решающую проверку: расхождение −14 %. M(T) применима | F61: =S61/R61^1.5 | G61: =T61/R61^2 | H61: =CHIDIST(D61,2) | I61: 0.74853487 | J61: 0.27705627 | K61: =z_p*STDEV('Метрики — ряд'!AO7:BW7)*SQRT(4) | L61: =PERCENTILE('Метрики — ряд'!BY7:DD7,p_conf) | M61: =(K61-L61)/ABS(L61)*100 | N61: =IF(K61>=O61,"ЗАМЕНА: вырожден",IF(ABS(M61)<=tau*100,"M(T) — совпадает",IF(M61<0,"ЗАМЕНА: занижает","M(T) — консервативна"))) | O61: ='Метрики'!C12 | P61: =COUNT('Метрики — ряд'!AO7:BW7) | Q61: =AVERAGE('Метрики — ряд'!AO7:BW7) | R61: =SUMPRODUCT(('Метрики — ряд'!AO7:BW7-Q61)^2)/P61 | S61: =SUMPRODUCT(('Метрики — ряд'!AO7:BW7-Q61)^3)/P61 | T61: =SUMPRODUCT(('Метрики — ряд'!AO7:BW7-Q61)^4)/P61
A62: EL — прочие | B62: Метрики — ряд!AO8:BW8 | C62: =IF(AND(H62>alpha,I62>alpha,J62<ad_crit),"нормально","НЕ нормально") | D62: =P62/6*(F62^2+(G62-3)^2/4) | E62: Завышение 120 % по той же причине, что у EL общего — снос вниз | F62: =S62/R62^1.5 | G62: =T62/R62^2 | H62: =CHIDIST(D62,2) | I62: 0.69511836 | J62: 0.32170749 | K62: =z_p*STDEV('Метрики — ряд'!AO8:BW8)*SQRT(4) | L62: =PERCENTILE('Метрики — ряд'!BY8:DD8,p_conf) | M62: =(K62-L62)/ABS(L62)*100 | N62: =IF(K62>=O62,"ЗАМЕНА: вырожден",IF(ABS(M62)<=tau*100,"M(T) — совпадает",IF(M62<0,"ЗАМЕНА: занижает","M(T) — консервативна"))) | O62: ='Метрики'!C13 | P62: =COUNT('Метрики — ряд'!AO8:BW8) | Q62: =AVERAGE('Метрики — ряд'!AO8:BW8) | R62: =SUMPRODUCT(('Метрики — ряд'!AO8:BW8-Q62)^2)/P62 | S62: =SUMPRODUCT(('Метрики — ряд'!AO8:BW8-Q62)^3)/P62 | T62: =SUMPRODUCT(('Метрики — ряд'!AO8:BW8-Q62)^4)/P62
A63: PD — необеспеченные | B63: Метрики — ряд!AO9:BW9 | C63: =IF(AND(H63>alpha,I63>alpha,J63<ad_crit),"нормально","НЕ нормально") | D63: =P63/6*(F63^2+(G63-3)^2/4) | E63: Завышение 83 %: PD падает с 12,13 до 10,96 за девять кварталов | F63: =S63/R63^1.5 | G63: =T63/R63^2 | H63: =CHIDIST(D63,2) | I63: 0.010479863 | J63: 1.2159614 | K63: =z_p*STDEV('Метрики — ряд'!AO9:BW9)*SQRT(4) | L63: =PERCENTILE('Метрики — ряд'!BY9:DD9,p_conf) | M63: =(K63-L63)/ABS(L63)*100 | N63: =IF(K63>=O63,"ЗАМЕНА: вырожден",IF(ABS(M63)<=tau*100,"M(T) — совпадает",IF(M63<0,"ЗАМЕНА: занижает","M(T) — консервативна"))) | O63: ='Метрики'!C14 | P63: =COUNT('Метрики — ряд'!AO9:BW9) | Q63: =AVERAGE('Метрики — ряд'!AO9:BW9) | R63: =SUMPRODUCT(('Метрики — ряд'!AO9:BW9-Q63)^2)/P63 | S63: =SUMPRODUCT(('Метрики — ряд'!AO9:BW9-Q63)^3)/P63 | T63: =SUMPRODUCT(('Метрики — ряд'!AO9:BW9-Q63)^4)/P63
A64: PD — необеспеченные, наличные | B64: Метрики — ряд!AO10:BW10 | C64: =IF(AND(H64>alpha,I64>alpha,J64<ad_crit),"нормально","НЕ нормально") | D64: =P64/6*(F64^2+(G64-3)^2/4) | E64: Завышение 68 %, та же причина | F64: =S64/R64^1.5 | G64: =T64/R64^2 | H64: =CHIDIST(D64,2) | I64: 0.0036287999 | J64: 1.403588 | K64: =z_p*STDEV('Метрики — ряд'!AO10:BW10)*SQRT(4) | L64: =PERCENTILE('Метрики — ряд'!BY10:DD10,p_conf) | M64: =(K64-L64)/ABS(L64)*100 | N64: =IF(K64>=O64,"ЗАМЕНА: вырожден",IF(ABS(M64)<=tau*100,"M(T) — совпадает",IF(M64<0,"ЗАМЕНА: занижает","M(T) — консервативна"))) | O64: ='Метрики'!C15 | P64: =COUNT('Метрики — ряд'!AO10:BW10) | Q64: =AVERAGE('Метрики — ряд'!AO10:BW10) | R64: =SUMPRODUCT(('Метрики — ряд'!AO10:BW10-Q64)^2)/P64 | S64: =SUMPRODUCT(('Метрики — ряд'!AO10:BW10-Q64)^3)/P64 | T64: =SUMPRODUCT(('Метрики — ряд'!AO10:BW10-Q64)^4)/P64
A65: PD — необеспеченные, товарные | B65: Метрики — ряд!AO11:BW11 | C65: =IF(AND(H65>alpha,I65>alpha,J65<ad_crit),"нормально","НЕ нормально") | D65: =P65/6*(F65^2+(G65-3)^2/4) | E65: Завышение 523 % — крайний случай сноса: четырёхмесячный рост почти отсутствует, весь ход направлен вниз | F65: =S65/R65^1.5 | G65: =T65/R65^2 | H65: =CHIDIST(D65,2) | I65: 0.0054344101 | J65: 1.1822941 | K65: =z_p*STDEV('Метрики — ряд'!AO11:BW11)*SQRT(4) | L65: =PERCENTILE('Метрики — ряд'!BY11:DD11,p_conf) | M65: =(K65-L65)/ABS(L65)*100 | N65: =IF(K65>=O65,"ЗАМЕНА: вырожден",IF(ABS(M65)<=tau*100,"M(T) — совпадает",IF(M65<0,"ЗАМЕНА: занижает","M(T) — консервативна"))) | O65: ='Метрики'!C16 | P65: =COUNT('Метрики — ряд'!AO11:BW11) | Q65: =AVERAGE('Метрики — ряд'!AO11:BW11) | R65: =SUMPRODUCT(('Метрики — ряд'!AO11:BW11-Q65)^2)/P65 | S65: =SUMPRODUCT(('Метрики — ряд'!AO11:BW11-Q65)^3)/P65 | T65: =SUMPRODUCT(('Метрики — ряд'!AO11:BW11-Q65)^4)/P65
A66: PD — обеспеченные | B66: Метрики — ряд!AO12:BW12 | C66: =IF(AND(H66>alpha,I66>alpha,J66<ad_crit),"нормально","НЕ нормально") | D66: =P66/6*(F66^2+(G66-3)^2/4) | E66: Расхождение −19 %, внутри порога по модулю, но со знаком «минус»: модель чуть уже факта. Остаётся на M(T), отмечено | F66: =S66/R66^1.5 | G66: =T66/R66^2 | H66: =CHIDIST(D66,2) | I66: 0.0018761219 | J66: 1.6158868 | K66: =z_p*STDEV('Метрики — ряд'!AO12:BW12)*SQRT(4) | L66: =PERCENTILE('Метрики — ряд'!BY12:DD12,p_conf) | M66: =(K66-L66)/ABS(L66)*100 | N66: =IF(K66>=O66,"ЗАМЕНА: вырожден",IF(ABS(M66)<=tau*100,"M(T) — совпадает",IF(M66<0,"ЗАМЕНА: занижает","M(T) — консервативна"))) | O66: ='Метрики'!C17 | P66: =COUNT('Метрики — ряд'!AO12:BW12) | Q66: =AVERAGE('Метрики — ряд'!AO12:BW12) | R66: =SUMPRODUCT(('Метрики — ряд'!AO12:BW12-Q66)^2)/P66 | S66: =SUMPRODUCT(('Метрики — ряд'!AO12:BW12-Q66)^3)/P66 | T66: =SUMPRODUCT(('Метрики — ряд'!AO12:BW12-Q66)^4)/P66
A67: PD — прочие | B67: Метрики — ряд!AO13:BW13 | C67: =IF(AND(H67>alpha,I67>alpha,J67<ad_crit),"нормально","НЕ нормально") | D67: =P67/6*(F67^2+(G67-3)^2/4) | E67: Завышение 92 %, снос вниз | F67: =S67/R67^1.5 | G67: =T67/R67^2 | H67: =CHIDIST(D67,2) | I67: 0.064779724 | J67: 0.77572318 | K67: =z_p*STDEV('Метрики — ряд'!AO13:BW13)*SQRT(4) | L67: =PERCENTILE('Метрики — ряд'!BY13:DD13,p_conf) | M67: =(K67-L67)/ABS(L67)*100 | N67: =IF(K67>=O67,"ЗАМЕНА: вырожден",IF(ABS(M67)<=tau*100,"M(T) — совпадает",IF(M67<0,"ЗАМЕНА: занижает","M(T) — консервативна"))) | O67: ='Метрики'!C18 | P67: =COUNT('Метрики — ряд'!AO13:BW13) | Q67: =AVERAGE('Метрики — ряд'!AO13:BW13) | R67: =SUMPRODUCT(('Метрики — ряд'!AO13:BW13-Q67)^2)/P67 | S67: =SUMPRODUCT(('Метрики — ряд'!AO13:BW13-Q67)^3)/P67 | T67: =SUMPRODUCT(('Метрики — ряд'!AO13:BW13-Q67)^4)/P67

Sheet Обоснование методов
A1: Обоснование двух методов разметки зон
A2: Блоки 1–4 обосновывают ЗАПАС ВРЕМЕНИ M(T) = z(p)·σ_Δ·√T: формула держится на трёх допущениях (приросты независимы — отсюда √T, распределение суммы близко к нормальному — отсюда z, дрейфа нет), и каждое проверено на нашем же ряде. Блок 5 обосновывает ВТОРОЙ МЕТОД — эмпирический квантиль, которым размечается метрика, не прошедшая решающую проверку. Какая метрика каким методом размечена — на листе «Расчёт», блок 8; сами зоны — на «Метрики». Колонки G–K — служебные: T-месячные изменения, по которым считаются проверки.
A4: Проверка | B4: Что именно проверяется | C4: Формула в этой книге | D4: Значение | E4: Как читать | G4: Изменение за 1 мес. | H4: Изменение за 2 мес. | I4: Изменение за 3 мес. | J4: Изменение за 4 мес. | K4: Изменение за 6 мес.
A5: 1. Независимость приростов — единственное, на чём держится √T | G5: =Ряд!H6-Ряд!H5 | H5: =Ряд!H7-Ряд!H5 | I5: =Ряд!H8-Ряд!H5 | J5: =Ряд!H9-Ряд!H5 | K5: =Ряд!H11-Ряд!H5
A6: Автокорреляция лага 1 | B6: связь прироста с предыдущим приростом | C6: CORREL(Ряд!J7:J40,Ряд!J6:J39) | D6: =CORREL(Ряд!J7:J40,Ряд!J6:J39) | E6: новое, 14.09.2026 | G6: =Ряд!H7-Ряд!H6 | H6: =Ряд!H8-Ряд!H6 | I6: =Ряд!H9-Ряд!H6 | J6: =Ряд!H10-Ряд!H6 | K6: =Ряд!H12-Ряд!H6
A7: Порог значимости 2/√n | B7: выше этого значения автокорреляцию нельзя считать шумом | C7: 2/SQRT(COUNT(d)) | D7: =2/SQRT(COUNT(d)) | E7: новое | G7: =Ряд!H8-Ряд!H7 | H7: =Ряд!H9-Ряд!H7 | I7: =Ряд!H10-Ряд!H7 | J7: =Ряд!H11-Ряд!H7 | K7: =Ряд!H13-Ряд!H7
A8: |−0,083| против порога 0,338 — свидетельств против независимости нет. Это НЕ доказательство независимости: при 35 наблюдениях тест почти лишён мощности. Сказать об этом надо самим, иначе скажет оппонент. | G8: =Ряд!H9-Ряд!H8 | H8: =Ряд!H10-Ряд!H8 | I8: =Ряд!H11-Ряд!H8 | J8: =Ряд!H12-Ряд!H8 | K8: =Ряд!H14-Ряд!H8
A9: Фактическое с.к.о. изменений за 1 мес. | B9: разброс реальных 1-месячных изменений ряда | C9: STDEV($G$5:$G$39) | D9: =STDEV($G$5:$G$39) | E9: новое | G9: =Ряд!H10-Ряд!H9 | H9: =Ряд!H11-Ряд!H9 | I9: =Ряд!H12-Ряд!H9 | J9: =Ряд!H13-Ряд!H9 | K9: =Ряд!H15-Ряд!H9
A10: Отношение факт / модель при T = 1 | B10: во сколько раз реальный разброс отличается от σ_Δ·√1 | C10: D9/('Расчёт'!D6*SQRT(1)) | D10: =D9/('Расчёт'!D6*SQRT(1)) | E10: новое | G10: =Ряд!H11-Ряд!H10 | H10: =Ряд!H12-Ряд!H10 | I10: =Ряд!H13-Ряд!H10 | J10: =Ряд!H14-Ряд!H10 | K10: =Ряд!H16-Ряд!H10
A11: Фактическое с.к.о. изменений за 2 мес. | B11: разброс реальных 2-месячных изменений ряда | C11: STDEV($H$5:$H$38) | D11: =STDEV($H$5:$H$38) | E11: новое | G11: =Ряд!H12-Ряд!H11 | H11: =Ряд!H13-Ряд!H11 | I11: =Ряд!H14-Ряд!H11 | J11: =Ряд!H15-Ряд!H11 | K11: =Ряд!H17-Ряд!H11
A12: Отношение факт / модель при T = 2 | B12: во сколько раз реальный разброс отличается от σ_Δ·√2 | C12: D11/('Расчёт'!D6*SQRT(2)) | D12: =D11/('Расчёт'!D6*SQRT(2)) | E12: новое | G12: =Ряд!H13-Ряд!H12 | H12: =Ряд!H14-Ряд!H12 | I12: =Ряд!H15-Ряд!H12 | J12: =Ряд!H16-Ряд!H12 | K12: =Ряд!H18-Ряд!H12
A13: Фактическое с.к.о. изменений за 3 мес. | B13: разброс реальных 3-месячных изменений ряда | C13: STDEV($I$5:$I$37) | D13: =STDEV($I$5:$I$37) | E13: новое | G13: =Ряд!H14-Ряд!H13 | H13: =Ряд!H15-Ряд!H13 | I13: =Ряд!H16-Ряд!H13 | J13: =Ряд!H17-Ряд!H13 | K13: =Ряд!H19-Ряд!H13
A14: Отношение факт / модель при T = 3 | B14: во сколько раз реальный разброс отличается от σ_Δ·√3 | C14: D13/('Расчёт'!D6*SQRT(3)) | D14: =D13/('Расчёт'!D6*SQRT(3)) | E14: новое | G14: =Ряд!H15-Ряд!H14 | H14: =Ряд!H16-Ряд!H14 | I14: =Ряд!H17-Ряд!H14 | J14: =Ряд!H18-Ряд!H14 | K14: =Ряд!H20-Ряд!H14
A15: Фактическое с.к.о. изменений за 4 мес. | B15: разброс реальных 4-месячных изменений ряда | C15: STDEV($J$5:$J$36) | D15: =STDEV($J$5:$J$36) | E15: новое | G15: =Ряд!H16-Ряд!H15 | H15: =Ряд!H17-Ряд!H15 | I15: =Ряд!H18-Ряд!H15 | J15: =Ряд!H19-Ряд!H15 | K15: =Ряд!H21-Ряд!H15
A16: Отношение факт / модель при T = 4 | B16: во сколько раз реальный разброс отличается от σ_Δ·√4 | C16: D15/('Расчёт'!D6*SQRT(4)) | D16: =D15/('Расчёт'!D6*SQRT(4)) | E16: новое | G16: =Ряд!H17-Ряд!H16 | H16: =Ряд!H18-Ряд!H16 | I16: =Ряд!H19-Ряд!H16 | J16: =Ряд!H20-Ряд!H16 | K16: =Ряд!H22-Ряд!H16
A17: Фактическое с.к.о. изменений за 6 мес. | B17: разброс реальных 6-месячных изменений ряда | C17: STDEV($K$5:$K$34) | D17: =STDEV($K$5:$K$34) | E17: новое | G17: =Ряд!H18-Ряд!H17 | H17: =Ряд!H19-Ряд!H17 | I17: =Ряд!H20-Ряд!H17 | J17: =Ряд!H21-Ряд!H17 | K17: =Ряд!H23-Ряд!H17
A18: Отношение факт / модель при T = 6 | B18: во сколько раз реальный разброс отличается от σ_Δ·√6 | C18: D17/('Расчёт'!D6*SQRT(6)) | D18: =D17/('Расчёт'!D6*SQRT(6)) | E18: новое | G18: =Ряд!H19-Ряд!H18 | H18: =Ряд!H20-Ряд!H18 | I18: =Ряд!H21-Ряд!H18 | J18: =Ряд!H22-Ряд!H18 | K18: =Ряд!H24-Ряд!H18
A19: Отношение ниже единицы означает, что √T ЗАВЫШАЕТ разброс: ряд слегка возвращается к среднему. На T = 3 завышение 9 %, на T = 6 — 23 %. Для буфера это ошибка в безопасную сторону — жёлтая линия ниже, предупреждение раньше. Оговорка: окна перекрываются, поэтому это оценка, а не точное измерение. | G19: =Ряд!H20-Ряд!H19 | H19: =Ряд!H21-Ряд!H19 | I19: =Ряд!H22-Ряд!H19 | J19: =Ряд!H23-Ряд!H19 | K19: =Ряд!H25-Ряд!H19
A20: 2. Нормальность — и почему нужна не та, о которой спрашивают | G20: =Ряд!H21-Ряд!H20 | H20: =Ряд!H22-Ряд!H20 | I20: =Ряд!H23-Ряд!H20 | J20: =Ряд!H24-Ряд!H20 | K20: =Ряд!H26-Ряд!H20
A21: Асимметрия приростов | B21: скошенность месячных приростов: третий момент / σ³ | C21: (SUMPRODUCT((d-AVERAGE(d))^3)/COUNT(d))/(SUMPRODUCT((d-AVERAGE(d))^2)/COUNT(d))^1.5 | D21: =(SUMPRODUCT((d-AVERAGE(d))^3)/COUNT(d))/(SUMPRODUCT((d-AVERAGE(d))^2)/COUNT(d))^1.5 | E21: новое | G21: =Ряд!H22-Ряд!H21 | H21: =Ряд!H23-Ряд!H21 | I21: =Ряд!H24-Ряд!H21 | J21: =Ряд!H25-Ряд!H21 | K21: =Ряд!H27-Ряд!H21
A22: Избыточный эксцесс приростов | B22: толщина хвостов приростов: четвёртый момент / σ⁴ − 3 | C22: (SUMPRODUCT((d-AVERAGE(d))^4)/COUNT(d))/(SUMPRODUCT((d-AVERAGE(d))^2)/COUNT(d))^2-3 | D22: =(SUMPRODUCT((d-AVERAGE(d))^4)/COUNT(d))/(SUMPRODUCT((d-AVERAGE(d))^2)/COUNT(d))^2-3 | E22: новое | G22: =Ряд!H23-Ряд!H22 | H22: =Ряд!H24-Ряд!H22 | I22: =Ряд!H25-Ряд!H22 | J22: =Ряд!H26-Ряд!H22 | K22: =Ряд!H28-Ряд!H22
A23: Жарк–Бера по приростам | B23: сводный тест нормальности: n/6 × (g1² + g2²/4) | C23: COUNT(d)/6*(D21^2+D22^2/4) | D23: =COUNT(d)/6*(D21^2+D22^2/4) | E23: новое | G23: =Ряд!H24-Ряд!H23 | H23: =Ряд!H25-Ряд!H23 | I23: =Ряд!H26-Ряд!H23 | J23: =Ряд!H27-Ряд!H23 | K23: =Ряд!H29-Ряд!H23
A24: Критическое значение 5 % | B24: порог хи-квадрат с 2 степенями свободы; выше него нормальность отвергается | C24: 5.991 | D24: =5.991 | E24: статистическая таблица | G24: =Ряд!H25-Ряд!H24 | H24: =Ряд!H26-Ряд!H24 | I24: =Ряд!H27-Ряд!H24 | J24: =Ряд!H28-Ряд!H24 | K24: =Ряд!H30-Ряд!H24
A25: Асимметрия 3-месячных изменений | B25: скошенность того, к чему буфер реально применяется | C25: (SUMPRODUCT(($I$5:$I$37-AVERAGE($I$5:$I$37))^3)/COUNT($I$5:$I$37))/(SUMPRODUCT(($I$5:$I$37-AVERAGE($I$5:$I$37))^2)/COUNT($I$5:$I$37))^1.5 | D25: =(SUMPRODUCT(($I$5:$I$37-AVERAGE($I$5:$I$37))^3)/COUNT($I$5:$I$37))/(SUMPRODUCT(($I$5:$I$37-AVERAGE($I$5:$I$37))^2)/COUNT($I$5:$I$37))^1.5 | E25: новое | G25: =Ряд!H26-Ряд!H25 | H25: =Ряд!H27-Ряд!H25 | I25: =Ряд!H28-Ряд!H25 | J25: =Ряд!H29-Ряд!H25 | K25: =Ряд!H31-Ряд!H25
A26: Избыточный эксцесс 3-месячных изменений | B26: толщина хвостов трёхмесячной суммы | C26: (SUMPRODUCT(($I$5:$I$37-AVERAGE($I$5:$I$37))^4)/COUNT($I$5:$I$37))/(SUMPRODUCT(($I$5:$I$37-AVERAGE($I$5:$I$37))^2)/COUNT($I$5:$I$37))^2-3 | D26: =(SUMPRODUCT(($I$5:$I$37-AVERAGE($I$5:$I$37))^4)/COUNT($I$5:$I$37))/(SUMPRODUCT(($I$5:$I$37-AVERAGE($I$5:$I$37))^2)/COUNT($I$5:$I$37))^2-3 | E26: новое | G26: =Ряд!H27-Ряд!H26 | H26: =Ряд!H28-Ряд!H26 | I26: =Ряд!H29-Ряд!H26 | J26: =Ряд!H30-Ряд!H26 | K26: =Ряд!H32-Ряд!H26
A27: Жарк–Бера по 3-месячным изменениям | B27: тот же тест на трёхмесячной сумме | C27: COUNT($I$5:$I$37)/6*(D25^2+D26^2/4) | D27: =COUNT($I$5:$I$37)/6*(D25^2+D26^2/4) | E27: новое | G27: =Ряд!H28-Ряд!H27 | H27: =Ряд!H29-Ряд!H27 | I27: =Ряд!H30-Ряд!H27 | J27: =Ряд!H31-Ряд!H27 | K27: =Ряд!H33-Ряд!H27
A28: Что предсказывает ЦПТ | B28: асимметрия суммы трёх независимых = g1 / √3 | C28: D21/SQRT(3) | D28: =D21/SQRT(3) | E28: новое | G28: =Ряд!H29-Ряд!H28 | H28: =Ряд!H30-Ряд!H28 | I28: =Ряд!H31-Ряд!H28 | J28: =Ряд!H32-Ряд!H28 | K28: =Ряд!H34-Ряд!H28
A29: Главный довод: буфер применяется не к приростам, а к их трёхмесячной СУММЕ. У приростов асимметрия 0,67 — заметная. У трёхмесячной суммы 0,04, то есть она исчезла, и даже быстрее, чем требовала ЦПТ (0,39). Жарк–Бера 2,70 против критических 5,99 — нормальность не отвергается даже на приростах. И третье: z(0,90) = 1,28 лежит в теле распределения, а не в хвосте; ошибки нормальности бьют на 99 % и 99,9 %, а не на 90 %. | G29: =Ряд!H30-Ряд!H29 | H29: =Ряд!H31-Ряд!H29 | I29: =Ряд!H32-Ряд!H29 | J29: =Ряд!H33-Ряд!H29 | K29: =Ряд!H35-Ряд!H29
A30: 3. Буфер M(3) четырьмя независимыми способами | G30: =Ряд!H31-Ряд!H30 | H30: =Ряд!H32-Ряд!H30 | I30: =Ряд!H33-Ряд!H30 | J30: =Ряд!H34-Ряд!H30 | K30: =Ряд!H36-Ряд!H30
A31: Нормальная модель z·σ_Δ·√3 | B31: то, что стоит в расчёте | C31: z_p*'Расчёт'!D6*SQRT(3) | D31: =z_p*'Расчёт'!D6*SQRT(3) | E31: DISCLOSURE § 2.3 | G31: =Ряд!H32-Ряд!H31 | H31: =Ряд!H33-Ряд!H31 | I31: =Ряд!H34-Ряд!H31 | J31: =Ряд!H35-Ряд!H31 | K31: =Ряд!H37-Ряд!H31
A32: Эмпирический 90-й процентиль | B32: 90 % реальных 3-месячных изменений не превысили эту величину | C32: PERCENTILE($I$5:$I$37,p_conf) | D32: =PERCENTILE($I$5:$I$37,p_conf) | E32: новое | G32: =Ряд!H33-Ряд!H32 | H32: =Ряд!H34-Ряд!H32 | I32: =Ряд!H35-Ряд!H32 | J32: =Ряд!H36-Ряд!H32 | K32: =Ряд!H38-Ряд!H32
A33: Корниш–Фишер | B33: нормальный квантиль с поправкой на асимметрию и эксцесс суммы | C33: (z_p+(z_p^2-1)/6*D21/SQRT(3)+(z_p^3-3*z_p)/24*D22/3-(2*z_p^3-5*z_p)/36*(D21/SQRT(3))^2)*'Расчёт'!D6*SQRT(3) | D33: =(z_p+(z_p^2-1)/6*D21/SQRT(3)+(z_p^3-3*z_p)/24*D22/3-(2*z_p^3-5*z_p)/36*(D21/SQRT(3))^2)*'Расчёт'!D6*SQRT(3) | E33: новое | G33: =Ряд!H34-Ряд!H33 | H33: =Ряд!H35-Ряд!H33 | I33: =Ряд!H36-Ряд!H33 | J33: =Ряд!H37-Ряд!H33 | K33: =Ряд!H39-Ряд!H33
A34: Разброс трёх способов, % | B34: насколько максимальный ответ выше минимального | C34: MAX(D31,D32,D33)/MIN(D31,D32,D33)*100-100 | D34: =MAX(D31,D32,D33)/MIN(D31,D32,D33)*100-100 | E34: новое | G34: =Ряд!H35-Ряд!H34 | H34: =Ряд!H36-Ряд!H34 | I34: =Ряд!H37-Ряд!H34 | J34: =Ряд!H38-Ряд!H34 | K34: =Ряд!H40-Ряд!H34
A35: Стандартная ошибка самой σ_Δ | B35: точность оценки σ по 35 наблюдениям: σ / √(2(n−1)) | C35: 'Расчёт'!D6/SQRT(2*(COUNT(d)-1)) | D35: ='Расчёт'!D6/SQRT(2*(COUNT(d)-1)) | E35: новое | G35: =Ряд!H36-Ряд!H35 | H35: =Ряд!H37-Ряд!H35 | I35: =Ряд!H38-Ряд!H35 | J35: =Ряд!H39-Ряд!H35
A36: Она же в единицах M(3) | B36: z · SE(σ) · √3 — неопределённость буфера | C36: z_p*D35*SQRT(3) | D36: =z_p*D35*SQRT(3) | E36: новое | G36: =Ряд!H37-Ряд!H36 | H36: =Ряд!H38-Ряд!H36 | I36: =Ряд!H39-Ряд!H36 | J36: =Ряд!H40-Ряд!H36
A37: Все три непараметрических способа дают буфер ВЫШЕ нормальной модели, разброс 3,6 %. Направление систематическое: нормальная модель тонковата примерно на 0,33 пп. Поправка сознательно не вносится — собственная погрешность σ_Δ равна ±1,09 пп, то есть втрое больше смещения. Но записано это должно быть явно: ровно за молчание о выборе σ мы критикуем метод B в Р-Д1. Четвёртый способ — бутстрап 200 тыс. сумм трёх случайно взятых приростов — даёт 9,3688; в Excel без макросов он не воспроизводится и потому в таблицу не вынесен. | G37: =Ряд!H38-Ряд!H37 | H37: =Ряд!H39-Ряд!H37 | I37: =Ряд!H40-Ряд!H37
A38: 4. Дрейф | G38: =Ряд!H39-Ряд!H38 | H38: =Ряд!H40-Ряд!H38
A39: Средний прирост за месяц | B39: есть ли систематический снос ряда вверх | C39: AVERAGE(d) | D39: =AVERAGE(d) | E39: новое | G39: =Ряд!H40-Ряд!H39
A40: Дрейф за 3 месяца | B40: во что он превращается на горизонте буфера | C40: AVERAGE(d)*3 | D40: =AVERAGE(d)*3 | E40: новое
A41: 0,10 пп против буфера 9,03 — меньше 1 %. Допущение нулевого дрейфа безвредно, слагаемое μ·T в формулу не добавляется.
A42: 5. Обоснование второго метода: эмпирический квантиль
A43: Калибровка порога: выше 89 % лимита сигнальный уровень теряет две трети запаса времени. Данные не затронуты переходом на лестницу — считаны по top20_signal_calibration.csv.
A44: Модельный буфер CoR КБ/ПБ на 4 мес. | B44: z · σ_Δ · √4 по всему ряду | C44: z_p*STDEV(d_cor_kb)*SQRT(4) | D44: =z_p*STDEV(d_cor_kb)*SQRT(4) | E44: «Расчёт» блок 8
A45: Лимит той же метрики | B45: Приложение № 3 к Политике | C45: 'Метрики'!C6 | D45: ='Метрики'!C6 | E45: «Метрики» C6
A46: Буфер больше лимита на 9,5 %. Формально это крайний случай завышения — то есть ошибка в безопасную сторону. Практически зона исчезает: любое значение метрики оказывается либо жёлтым, либо красным, и лампа перестаёт нести информацию. Замена нужна по ПОЛЕЗНОСТИ, а не по безопасности, и это разные основания — их нельзя подменять одно другим.
A47: Эмпирический буфер, обычные месяцы, 4 мес. | B47: 90-й процентиль фактических изменений за 4 месяца | C47: PERCENTILE('Ряд'!Y9:Y40,p_conf) | D47: =PERCENTILE('Ряд'!Y9:Y40,p_conf) | E47: «Метрики» J6
A48: Он же в окне закрытия | B48: то же по февралю-марту | C48: PERCENTILE('Ряд'!Z9:Z40,p_conf) | D48: =PERCENTILE('Ряд'!Z9:Z40,p_conf) | E48: «Метрики» J7
A49: Метод не самодельный: BCBS d457 (MAR30) допускает историческую симуляцию наравне с параметрической моделью, и при тяжёлых хвостах она в практике преобладает. Предположения о форме распределения нет вовсе — берётся то, что ряд показал. Для CoR у метода есть и второе преимущество: календарный режим (Г36) попадает в эмпирическое распределение сам, в своей естественной доле, тогда как единая σ его размазывает по всему году.
A50: σ приращений CoR КБ/ПБ, обычные месяцы | B50: по 29 приращениям вне фев-марта | C50: STDEV('Ряд'!U6:U40) | D50: =STDEV('Ряд'!U6:U40) | E50: «Метрики» E6
A51: σ тех же приращений в окне закрытия | B51: по 6 приращениям фев-марта | C51: STDEV('Ряд'!V6:V40) | D51: =STDEV('Ряд'!V6:V40) | E51: «Метрики» E7
A52: Во сколько раз режимы различаются | B52: σ закрытия / σ обычных месяцев | C52: STDEV('Ряд'!V6:V40)/STDEV('Ряд'!U6:U40) | D52: =STDEV('Ряд'!V6:V40)/STDEV('Ряд'!U6:U40) | E52: Г36
A53: ЦЕНА МЕТОДА, которую объявляют вместе с числом. Первое: окна перекрываются — на 36 точках при T = 4 их 32, но независимых восемь, а в окне закрытия приращений всего шесть. Квантиль 0,90 по шести есть фактически максимум выборки. Второе: эмпирический квантиль НЕ монотонен по T — у ряда с сильным трендом вниз 90-й процентиль четырёхмесячных изменений оказывается меньше месячного, и лестница переворачивается; на листе «Метрики» это выправлено явным МАКС, и там же сказано, где выправление сработало. Третье: метод берёт в зачёт прошлый тренд, тогда как M(T) считает снос нулевым — поэтому он НЕ применяется к девяти розничным метрикам, где он дал бы границы вплотную к лимиту.

Sheet Зоны
A1: Светофор: зоны, определения, границы, действия
A2: Определения зон — дословно п. 18 Правил № 86 (Правила формирования системы управления рисками и внутреннего контроля, постановление Правления АРРФР от 28.04.2026 № 86, Минюст № 38586 от 29.04.2026). Своих формулировок здесь нет. Границы считаются из волатильности самой метрики, лимит приходит из Приложения № 3 к Политике — подобранных чисел на листе нет ни одного.
A4: Зона | B4: Определение по п. 18 Правил № 86 | C4: Нижняя граница | D4: Верхняя граница | E4: Формула границы | F4: Набл. | G4: Доля, %
A5: Зелёная | B5: уровень, не требующий применения корректирующих мер | C5: — | D5: ='Расчёт'!D29 | E5: — … L − M(4) | F5: =COUNTIF(v,"<"&'Расчёт'!D29) | G5: =F5/COUNT(v)*100
A6: Жёлтая | B6: уровень, определённый как допустимый, но требующий отдельных корректирующих мер в действующих процедурах системы управления рисками с целью снижения уровня риска | C6: ='Расчёт'!D29 | D6: ='Расчёт'!D17 | E6: L − M(4) … L − M(1) | F6: =COUNTIFS(v,">="&'Расчёт'!D29,v,"<"&'Расчёт'!D17) | G6: =F6/COUNT(v)*100
A7: Красная | B7: уровень, определённый как высокий, требующий применения соответствующих мер с целью недопущения ухудшения финансовой устойчивости банка и его платёжеспособности | C7: ='Расчёт'!D17 | D7: ='Расчёт'!D12 | E7: L − M(1) … L | F7: =COUNTIFS(v,">="&'Расчёт'!D17,v,"<"&'Расчёт'!D12) | G7: =F7/COUNT(v)*100
A8: Нарушение лимита | B8: действующий уровень риск-аппетита превышен. Отдельное состояние, а не зона: зоны описывают уровень риска, лимит — обязательство | C8: ='Расчёт'!D12 | D8: — | E8: L … — | F8: =COUNTIF(v,">="&'Расчёт'!D12) | G8: =F8/COUNT(v)*100
A9: Всего | F9: =SUM(F5:F8) | G9: =F9/COUNT(v)*100
A11: Где мы сейчас, 01.07.2026
A12: Текущее значение метрики | B12: ='Расчёт'!D8 | C12: доля топ-20 в собственном капитале, балансовая база
A13: Граница зелёная / жёлтая | B13: ='Расчёт'!D29 | C13: L − M(4)
A14: Граница жёлтая / красная | B14: ='Расчёт'!D17 | C14: L − M(1)
A15: Лимит | B15: ='Расчёт'!D12 | C15: 95 % в регуляторной базе ÷ k
A16: До красной, пп | B16: ='Расчёт'!D17-'Расчёт'!D8 | C16: меньше половины одного месячного σ
A17: До лимита, пп | B17: ='Расчёт'!D12-'Расчёт'!D8
A18: T* — месяцев до лимита | B18: ='Расчёт'!D45 | C18: ((L − v) / (z·σ))²
A19: Зона текущей точки | B19: =IF('Расчёт'!D8>='Расчёт'!D12,"НАРУШЕНИЕ ЛИМИТА",IF('Расчёт'!D8>='Расчёт'!D17,"КРАСНАЯ",IF('Расчёт'!D8>='Расчёт'!D29,"ЖЁЛТАЯ","ЗЕЛЁНАЯ"))) | C19: Жёлтая означает: уровень допустим, но требует отдельных корректирующих мер в действующих процедурах.
A21: Сколько стоит смена зоны, млн ₸
A22: Что сделать | B22: Через задолженность топ-20 | C22: Через собственный капитал | D22: Комментарий
A23: Вернуться в зелёную | B23: ='Расчёт'!D29/100*Ряд!D40-Ряд!B40 | C23: =Ряд!B40/('Расчёт'!D29/100)-Ряд!D40 | D23: самая дорогая из трёх: 3,3 пп ниже текущей точки
A24: Не войти в красную | B24: ='Расчёт'!D17/100*Ряд!D40-Ряд!B40 | C24: =Ряд!B40/('Расчёт'!D17/100)-Ряд!D40 | D24: запас, который есть сейчас; один средний месяц по σ больше него вдвое
A25: Не нарушить лимит | B25: ='Расчёт'!D12/100*Ряд!D40-Ряд!B40 | C25: =Ряд!B40/('Расчёт'!D12/100)-Ряд!D40 | D25: формальный запас до обязательства
A26: Масштаб, определяющий всё остальное: одно среднее месячное движение по σ_Δ равно 17 989 млн ₸ задолженности при текущем капитале. Это вдвое больше запаса до красной зоны. Меры, которые начинают выбирать в момент срабатывания, опаздывают по построению — отсюда требование п. 18 № 86 брать их из ДЕЙСТВУЮЩИХ процедур, а не сочинять.
A28: Вероятность достичь границы за T месяцев
A29: Граница | B29: 1 месяц | C29: 2 месяца | D29: 3 месяца | E29: 6 месяцев | F29: Разрыв, пп
A30: Войти в красную зону | B30: =(1-NORMSDIST(('Расчёт'!D17-'Расчёт'!D8)/('Расчёт'!D6*SQRT(1))))*100 | C30: =(1-NORMSDIST(('Расчёт'!D17-'Расчёт'!D8)/('Расчёт'!D6*SQRT(2))))*100 | D30: =(1-NORMSDIST(('Расчёт'!D17-'Расчёт'!D8)/('Расчёт'!D6*SQRT(3))))*100 | E30: =(1-NORMSDIST(('Расчёт'!D17-'Расчёт'!D8)/('Расчёт'!D6*SQRT(6))))*100 | F30: ='Расчёт'!D17-'Расчёт'!D8
A31: Нарушить лимит | B31: =(1-NORMSDIST(('Расчёт'!D12-'Расчёт'!D8)/('Расчёт'!D6*SQRT(1))))*100 | C31: =(1-NORMSDIST(('Расчёт'!D12-'Расчёт'!D8)/('Расчёт'!D6*SQRT(2))))*100 | D31: =(1-NORMSDIST(('Расчёт'!D12-'Расчёт'!D8)/('Расчёт'!D6*SQRT(3))))*100 | E31: =(1-NORMSDIST(('Расчёт'!D12-'Расчёт'!D8)/('Расчёт'!D6*SQRT(6))))*100 | F31: ='Расчёт'!D12-'Расчёт'!D8
A32: Считано по нормальной модели с нулевым дрейфом — тем же допущением, что и M(T), и проверенным на листе «Обоснование M(T)». Главное число: вероятность войти в красную зону в течение одного месяца — около 32 %. Это не прогноз, а мера близости: разрыв до красной меньше половины месячного σ.
A34: План действий по зонам — предложение, требующее решений
A35: Зона | B35: Наблюдение | C35: Уведомление | D35: Меры | E35: Что документируется | F35: Вопрос, который надо закрыть
A36: Зелёная | B36: Ежемесячно, штатный отчёт | C36: Штатный отчёт | D36: Не требуются | E36: — | F36: Ничего. Формулировка зоны прямо говорит «не требующий мер» — добавлять действия сюда значит противоречить определению
A37: Жёлтая | B37: Еженедельно, с гистерезисом | C37: БРМ → КРВК, срок не установлен | D37: Из действующих процедур: получение денежного обеспечения (вычитается из числителя метрики напрямую); остановка прироста задолженности топ-20 и пролонгаций | E37: Решение о применении меры либо мотивированный отказ | F37: 1) Какие именно действующие процедуры содержат эти меры — норма требует брать существующие, а не вводить новые. 2) N месяцев подряд ниже границы для выхода из зоны (гистерезис). 3) Срок уведомления КРВК
A38: Красная | B38: Еженедельно + внеочередной расчёт | C38: СД через КРВК, незамедлительно | D38: Те же меры плюс план снижения с датой возврата в жёлтую. Синдикация и уступка части требуют контрагента и в один месяц не укладываются | E38: Письменный план устранения с ответственным и датой | F38: 1) Уведомляется ли АРРФР и на каком основании — смотреть Правила № 272 о мерах надзорного реагирования. 2) Согласование с триггерами режима восстановления по № 119: красная зона использует их словарь («финансовая устойчивость и платёжеспособность»), и две системы не должны противоречить
A39: Нарушение лимита | B39: Еженедельно + внеочередной расчёт | C39: СД, протокол УО | D39: Устранение нарушения по Политике п. 12-1 и п. 27 | E39: Письменное описание того, как нарушение будет или было устранено | F39: Конкретных мер и сроков в Политике НЕТ — это записанный пробел ВНД, а не пропуск в книге. Закрывается правкой Политики, не расчётом
A41: Структура режима взята из OCC Heightened Standards II.H (см. BENCHMARK.md): выявление; РАЗЛИЧЕНИЕ нарушений по тяжести последствий; протокол уведомления первой линии, БРМ, внутреннего аудита, СД и регулятора; письменное описание устранения; ответственность с учётом величины, частоты и повторяемости. Из пяти элементов в нашей Политике есть один — факт нарушения. Остальные четыре и есть содержание правки.
A42: ЧТО НА ЭТОМ ЛИСТЕ НЕ ДОКАЗАНО. Первое: п. 18 Правил № 86 и Приложение № 2 к Методике дословно не разобраны; определения зон взяты из конспекта SPRAVOCHNIK_RA.md, а не из оригинала. Второе, важнее: при лестничной разметке действующий уровень 95 %% выполняет роль риск-ёмкости, а уровнем риск-аппетита становится граница зелёной зоны — это смена смысла числа 95, и её принимает уполномоченный орган, а не расчёт. Находка Р1 показывает, что на восьми метриках Банк уже так и делает.
A43: Ряд и лестница зон. Собрано viz/zone_ladder.py из того же CSV, что и расчёт, — границы на картинке и в таблице совпадают по построению.
A79: Находка Р1: у восьми метрик, где зоны уже установлены, порог красной стоит ЗА уровнем риск-аппетита. Это довод за лестницу, и он не наш — так уже сделано в Банке.

Sheet Две сигмы
A1: Две σ в одной таблице методов — и они про разное
A2: Остаток находки Р-Д1. Третья σ принадлежала методу B, который из книги убран: он не защищается на комитете. В DISCLOSURE.md Р-Д1 остаётся целиком — там он про чужую опубликованную таблицу, а не про нашу книгу.
A4: Методы | B4: Какая σ | C4: Значение | D4: К σ_Δ | E4: Что из этого следует
A5: D, H | B5: выборочное с.к.о. приростов, все 35 | C5: ='Расчёт'!D6 | D5: =C5/'Расчёт'!D6 | E5: Базовая. На ней стоят запас M(T), расстояние D и T*
A6: М1 | B6: выборочное с.к.о. самих уровней, не приростов | C6: ='Расчёт'!D7 | D6: =C6/'Расчёт'!D6 | E6: Мера разброса уровня за три года, а не месячного хода. С первой несопоставима в принципе: одна про то, где ряд стоял, другая про то, как быстро он движется
A8: Правило, которое из этого остаётся: σ называется прямо в строке метода. Метод, защищаемый в собственных терминах, несравним с методом, защищаемым в своих, — и разница в 53 % между этими двумя σ тому иллюстрация.

Sheet Метрики
A1: Зоны по всем кредитным метрикам: чем посчитано и почему
A2: Одна страница на все зоны. Колонки F–I показывают, КАК посчитана каждая строка: эксцесс и p(Жарк-Бера) — из расчёта нормальности на листе «Расчёт», колонка I — вердикт решающей проверки оттуда же. Буфер в J и K берётся той формулой, которую этот вердикт назначил: z·σ·√T для нормальных, эмпирический 90-й процентиль фактических T-месячных изменений для остальных. ОДНО ИСКЛЮЧЕНИЕ: CoR МСБ вердиктом проходит на M(T), но размечена эмпирически ради сопоставимости с КБ/ПБ — это решение, а не вывод расчёта, и оно помечено в колонке X. Обоснование обоих методов — лист «Обоснование методов».
A4: Метрика | B4: Сегмент | C4: Лимит L | D4: Приращ. | E4: σ_Δ | F4: Экс. | G4: p(ЖБ) | H4: Нормально? | I4: МЕТОД | J4: Буфер 4 мес | K4: Буфер 1 мес | L4: Зел./жёлт. | M4: Жёлт./красн. | N4: Зел., % L | O4: Жёлт., % L | P4: Факт | Q4: Зона | R4: Расст., σ | S4: SE(σ) | T4: Зел. | U4: Жёлт. | V4: Красн. | W4: Наруш. | X4: Почему такой метод
A5: Топ-20 / собственный капитал | B5: KB | C5: ='Расчёт'!D12 | D5: =COUNT(d) | E5: ='Расчёт'!D6 | F5: ='Расчёт'!G56 | G5: ='Расчёт'!H56 | H5: ='Расчёт'!C56 | I5: =IF(LEFT('Расчёт'!N56,6)="ЗАМЕНА","ист. симуляция","M(T) = z·σ·√T") | J5: ='Расчёт'!D28 | K5: ='Расчёт'!D16 | L5: =C5-J5 | M5: =C5-K5 | N5: =L5/C5*100 | O5: =M5/C5*100 | P5: ='Расчёт'!D8 | Q5: =IF(P5>=C5,"НАРУШЕНИЕ",IF(P5>=M5,"КРАСНАЯ",IF(P5>=L5,"ЖЁЛТАЯ","зелёная"))) | R5: =(C5-P5)/E5 | S5: =E5/SQRT(2*(D5-1)) | T5: =COUNTIF(v,"<"&L5) | U5: =COUNTIF(v,"<"&M5)-T5 | V5: =COUNTIF(v,"<"&C5)-T5-U5 | W5: =COUNTIF(v,">="&C5) | X5: Единственная метрика, проходящая и три формальных критерия, и решающую проверку (расхождение +21 % при пороге 25 %). M(T) без оговорок
A6: CoR — стоимость риска (KB_PB) — обычные месяцы | B6: KB_PB | C6: 3 | D6: =COUNT('Ряд'!U6:U40) | E6: =STDEV('Ряд'!U6:U40) | F6: ='Расчёт'!G57 | G6: ='Расчёт'!H57 | H6: ='Расчёт'!C57 | I6: ="ист. симуляция — обычные месяцы" | J6: =MAX(PERCENTILE('Ряд'!Y9:Y40,p_conf),K6) | K6: =PERCENTILE('Ряд'!U6:U40,p_conf) | L6: =C6-J6 | M6: =C6-K6 | N6: =L6/C6*100 | O6: =M6/C6*100 | P6: ='Ряд'!O40 | Q6: =IF(P6>=C6,"НАРУШЕНИЕ",IF(P6>=M6,"КРАСНАЯ",IF(P6>=L6,"ЖЁЛТАЯ","зелёная"))) | R6: =(C6-P6)/E6 | S6: =E6/SQRT(2*(D6-1)) | T6: =COUNTIFS('Ряд'!$T$5:$T$40,0,cor_kb,"<"&L6) | U6: =COUNTIFS('Ряд'!$T$5:$T$40,0,cor_kb,"<"&M6)-T6 | V6: =COUNTIFS('Ряд'!$T$5:$T$40,0,cor_kb,"<"&C6)-T6-U6 | W6: =COUNTIFS('Ряд'!$T$5:$T$40,0,cor_kb,">="&C6) | X6: Замена: M(4) = 3,2850 больше самого лимита 3,00, граница зелёной уходила в минус — зона вырождалась. Эмпирический квантиль по обычным месяцам, σ здесь 0,5998 против смешанной 1,2817
A7: CoR — стоимость риска (KB_PB) — окно закрытия (фев–март) | B7: KB_PB | C7: 3 | D7: =COUNT('Ряд'!V6:V40) | E7: =STDEV('Ряд'!V6:V40) | F7: ='Расчёт'!G57 | G7: ='Расчёт'!H57 | H7: ='Расчёт'!C57 | I7: ="ист. симуляция — окно закрытия (фев–март)" | J7: =MAX(PERCENTILE('Ряд'!Z9:Z40,p_conf),K7) | K7: =PERCENTILE('Ряд'!V6:V40,p_conf) | L7: =C7-J7 | M7: =C7-K7 | N7: =L7/C7*100 | O7: =M7/C7*100 | P7: ='Ряд'!O40 | Q7: =IF(P7>=C7,"НАРУШЕНИЕ",IF(P7>=M7,"КРАСНАЯ",IF(P7>=L7,"ЖЁЛТАЯ","зелёная"))) | R7: =(C7-P7)/E7 | S7: =E7/SQRT(2*(D7-1)) | T7: =COUNTIFS('Ряд'!$T$5:$T$40,1,cor_kb,"<"&L7) | U7: =COUNTIFS('Ряд'!$T$5:$T$40,1,cor_kb,"<"&M7)-T7 | V7: =COUNTIFS('Ряд'!$T$5:$T$40,1,cor_kb,"<"&C7)-T7-U7 | W7: =COUNTIFS('Ряд'!$T$5:$T$40,1,cor_kb,">="&C7) | X7: Тот же метод, окно годового закрытия (февраль-март, Г36): σ здесь 3,0257, впятеро выше обычной. Лестница вырождается в ДВЕ зоны — Q90 четырёхмесячных изменений меньше месячного, выправлено МАКС
A8: CoR — стоимость риска (MSB) — обычные месяцы | B8: MSB | C8: 3.5 | D8: =COUNT('Ряд'!AA6:AA40) | E8: =STDEV('Ряд'!AA6:AA40) | F8: ='Расчёт'!G58 | G8: ='Расчёт'!H58 | H8: ='Расчёт'!C58 | I8: ="ист. симуляция — обычные месяцы" | J8: =MAX(PERCENTILE('Ряд'!AD9:AD40,p_conf),K8) | K8: =PERCENTILE('Ряд'!AA6:AA40,p_conf) | L8: =C8-J8 | M8: =C8-K8 | N8: =L8/C8*100 | O8: =M8/C8*100 | P8: ='Ряд'!R40 | Q8: =IF(P8>=C8,"НАРУШЕНИЕ",IF(P8>=M8,"КРАСНАЯ",IF(P8>=L8,"ЖЁЛТАЯ","зелёная"))) | R8: =(C8-P8)/E8 | S8: =E8/SQRT(2*(D8-1)) | T8: =COUNTIFS('Ряд'!$T$5:$T$40,0,cor_ms,"<"&L8) | U8: =COUNTIFS('Ряд'!$T$5:$T$40,0,cor_ms,"<"&M8)-T8 | V8: =COUNTIFS('Ряд'!$T$5:$T$40,0,cor_ms,"<"&C8)-T8-U8 | W8: =COUNTIFS('Ряд'!$T$5:$T$40,0,cor_ms,">="&C8) | X8: РЕШЕНИЕ, а не вердикт: сама по себе метрика проходит на M(T) (завышение 28,4 % — чуть выше порога 25 %), но размечена эмпирически ради сопоставимости с КБ/ПБ внутри пары CoR
A9: CoR — стоимость риска (MSB) — окно закрытия (фев–март) | B9: MSB | C9: 3.5 | D9: =COUNT('Ряд'!AB6:AB40) | E9: =STDEV('Ряд'!AB6:AB40) | F9: ='Расчёт'!G58 | G9: ='Расчёт'!H58 | H9: ='Расчёт'!C58 | I9: ="ист. симуляция — окно закрытия (фев–март)" | J9: =MAX(PERCENTILE('Ряд'!AE9:AE40,p_conf),K9) | K9: =PERCENTILE('Ряд'!AB6:AB40,p_conf) | L9: =C9-J9 | M9: =C9-K9 | N9: =L9/C9*100 | O9: =M9/C9*100 | P9: ='Ряд'!R40 | Q9: =IF(P9>=C9,"НАРУШЕНИЕ",IF(P9>=M9,"КРАСНАЯ",IF(P9>=L9,"ЖЁЛТАЯ","зелёная"))) | R9: =(C9-P9)/E9 | S9: =E9/SQRT(2*(D9-1)) | T9: =COUNTIFS('Ряд'!$T$5:$T$40,1,cor_ms,"<"&L9) | U9: =COUNTIFS('Ряд'!$T$5:$T$40,1,cor_ms,"<"&M9)-T9 | V9: =COUNTIFS('Ряд'!$T$5:$T$40,1,cor_ms,"<"&C9)-T9-U9 | W9: =COUNTIFS('Ряд'!$T$5:$T$40,1,cor_ms,">="&C9) | X9: Окно закрытия, σ 1,5441 против 0,3179 в обычные месяцы. Наблюдений шесть: квантиль 0,90 по ним есть фактически максимум выборки
A10: ='Метрики — ряд'!A5 | B10: ='Метрики — ряд'!B5 | C10: ='Метрики — ряд'!C5 | D10: =COUNT('Метрики — ряд'!AO5:BW5) | E10: =STDEV('Метрики — ряд'!AO5:BW5) | F10: ='Расчёт'!G59 | G10: ='Расчёт'!H59 | H10: ='Расчёт'!C59 | I10: =IF(LEFT('Расчёт'!N59,6)="ЗАМЕНА","ист. симуляция","M(T) = z·σ·√T") | J10: =z_p*E10*SQRT(4) | K10: =z_p*E10*SQRT(1) | L10: =C10-J10 | M10: =C10-K10 | N10: =L10/C10*100 | O10: =M10/C10*100 | P10: ='Метрики — ряд'!AM5 | Q10: =IF(P10>=C10,"НАРУШЕНИЕ",IF(P10>=M10,"КРАСНАЯ",IF(P10>=L10,"ЖЁЛТАЯ","зелёная"))) | R10: =(C10-P10)/E10 | S10: =E10/SQRT(2*(D10-1)) | T10: =COUNTIF('Метрики — ряд'!D5:AM5,"<"&L10) | U10: =COUNTIF('Метрики — ряд'!D5:AM5,"<"&M10)-T10 | V10: =COUNTIF('Метрики — ряд'!D5:AM5,"<"&C10)-T10-U10 | W10: =COUNTIF('Метрики — ряд'!D5:AM5,">="&C10) | X10: Решающая проверка: Завышение 128 % — снос, а не хвосты: метрика падает три года, а M(T) считает снос нулевым. Завышение безопасно
A11: ='Метрики — ряд'!A6 | B11: ='Метрики — ряд'!B6 | C11: ='Метрики — ряд'!C6 | D11: =COUNT('Метрики — ряд'!AO6:BW6) | E11: =STDEV('Метрики — ряд'!AO6:BW6) | F11: ='Расчёт'!G60 | G11: ='Расчёт'!H60 | H11: ='Расчёт'!C60 | I11: =IF(LEFT('Расчёт'!N60,6)="ЗАМЕНА","ист. симуляция","M(T) = z·σ·√T") | J11: =z_p*E11*SQRT(4) | K11: =z_p*E11*SQRT(1) | L11: =C11-J11 | M11: =C11-K11 | N11: =L11/C11*100 | O11: =M11/C11*100 | P11: ='Метрики — ряд'!AM6 | Q11: =IF(P11>=C11,"НАРУШЕНИЕ",IF(P11>=M11,"КРАСНАЯ",IF(P11>=L11,"ЖЁЛТАЯ","зелёная"))) | R11: =(C11-P11)/E11 | S11: =E11/SQRT(2*(D11-1)) | T11: =COUNTIF('Метрики — ряд'!D6:AM6,"<"&L11) | U11: =COUNTIF('Метрики — ряд'!D6:AM6,"<"&M11)-T11 | V11: =COUNTIF('Метрики — ряд'!D6:AM6,"<"&C11)-T11-U11 | W11: =COUNTIF('Метрики — ряд'!D6:AM6,">="&C11) | X11: Решающая проверка: Завышение 28 %, на границе порога. Остаётся на M(T)
A12: ='Метрики — ряд'!A7 | B12: ='Метрики — ряд'!B7 | C12: ='Метрики — ряд'!C7 | D12: =COUNT('Метрики — ряд'!AO7:BW7) | E12: =STDEV('Метрики — ряд'!AO7:BW7) | F12: ='Расчёт'!G61 | G12: ='Расчёт'!H61 | H12: ='Расчёт'!C61 | I12: =IF(LEFT('Расчёт'!N61,6)="ЗАМЕНА","ист. симуляция","M(T) = z·σ·√T") | J12: =z_p*E12*SQRT(4) | K12: =z_p*E12*SQRT(1) | L12: =C12-J12 | M12: =C12-K12 | N12: =L12/C12*100 | O12: =M12/C12*100 | P12: ='Метрики — ряд'!AM7 | Q12: =IF(P12>=C12,"НАРУШЕНИЕ",IF(P12>=M12,"КРАСНАЯ",IF(P12>=L12,"ЖЁЛТАЯ","зелёная"))) | R12: =(C12-P12)/E12 | S12: =E12/SQRT(2*(D12-1)) | T12: =COUNTIF('Метрики — ряд'!D7:AM7,"<"&L12) | U12: =COUNTIF('Метрики — ряд'!D7:AM7,"<"&M12)-T12 | V12: =COUNTIF('Метрики — ряд'!D7:AM7,"<"&C12)-T12-U12 | W12: =COUNTIF('Метрики — ряд'!D7:AM7,">="&C12) | X12: Решающая проверка: Проходит решающую проверку: расхождение −14 %. M(T) применима
A13: ='Метрики — ряд'!A8 | B13: ='Метрики — ряд'!B8 | C13: ='Метрики — ряд'!C8 | D13: =COUNT('Метрики — ряд'!AO8:BW8) | E13: =STDEV('Метрики — ряд'!AO8:BW8) | F13: ='Расчёт'!G62 | G13: ='Расчёт'!H62 | H13: ='Расчёт'!C62 | I13: =IF(LEFT('Расчёт'!N62,6)="ЗАМЕНА","ист. симуляция","M(T) = z·σ·√T") | J13: =z_p*E13*SQRT(4) | K13: =z_p*E13*SQRT(1) | L13: =C13-J13 | M13: =C13-K13 | N13: =L13/C13*100 | O13: =M13/C13*100 | P13: ='Метрики — ряд'!AM8 | Q13: =IF(P13>=C13,"НАРУШЕНИЕ",IF(P13>=M13,"КРАСНАЯ",IF(P13>=L13,"ЖЁЛТАЯ","зелёная"))) | R13: =(C13-P13)/E13 | S13: =E13/SQRT(2*(D13-1)) | T13: =COUNTIF('Метрики — ряд'!D8:AM8,"<"&L13) | U13: =COUNTIF('Метрики — ряд'!D8:AM8,"<"&M13)-T13 | V13: =COUNTIF('Метрики — ряд'!D8:AM8,"<"&C13)-T13-U13 | W13: =COUNTIF('Метрики — ряд'!D8:AM8,">="&C13) | X13: Решающая проверка: Завышение 120 % по той же причине, что у EL общего — снос вниз
A14: ='Метрики — ряд'!A9 | B14: ='Метрики — ряд'!B9 | C14: ='Метрики — ряд'!C9 | D14: =COUNT('Метрики — ряд'!AO9:BW9) | E14: =STDEV('Метрики — ряд'!AO9:BW9) | F14: ='Расчёт'!G63 | G14: ='Расчёт'!H63 | H14: ='Расчёт'!C63 | I14: =IF(LEFT('Расчёт'!N63,6)="ЗАМЕНА","ист. симуляция","M(T) = z·σ·√T") | J14: =z_p*E14*SQRT(4) | K14: =z_p*E14*SQRT(1) | L14: =C14-J14 | M14: =C14-K14 | N14: =L14/C14*100 | O14: =M14/C14*100 | P14: ='Метрики — ряд'!AM9 | Q14: =IF(P14>=C14,"НАРУШЕНИЕ",IF(P14>=M14,"КРАСНАЯ",IF(P14>=L14,"ЖЁЛТАЯ","зелёная"))) | R14: =(C14-P14)/E14 | S14: =E14/SQRT(2*(D14-1)) | T14: =COUNTIF('Метрики — ряд'!D9:AM9,"<"&L14) | U14: =COUNTIF('Метрики — ряд'!D9:AM9,"<"&M14)-T14 | V14: =COUNTIF('Метрики — ряд'!D9:AM9,"<"&C14)-T14-U14 | W14: =COUNTIF('Метрики — ряд'!D9:AM9,">="&C14) | X14: Решающая проверка: Завышение 83 %: PD падает с 12,13 до 10,96 за девять кварталов
A15: ='Метрики — ряд'!A10 | B15: ='Метрики — ряд'!B10 | C15: ='Метрики — ряд'!C10 | D15: =COUNT('Метрики — ряд'!AO10:BW10) | E15: =STDEV('Метрики — ряд'!AO10:BW10) | F15: ='Расчёт'!G64 | G15: ='Расчёт'!H64 | H15: ='Расчёт'!C64 | I15: =IF(LEFT('Расчёт'!N64,6)="ЗАМЕНА","ист. симуляция","M(T) = z·σ·√T") | J15: =z_p*E15*SQRT(4) | K15: =z_p*E15*SQRT(1) | L15: =C15-J15 | M15: =C15-K15 | N15: =L15/C15*100 | O15: =M15/C15*100 | P15: ='Метрики — ряд'!AM10 | Q15: =IF(P15>=C15,"НАРУШЕНИЕ",IF(P15>=M15,"КРАСНАЯ",IF(P15>=L15,"ЖЁЛТАЯ","зелёная"))) | R15: =(C15-P15)/E15 | S15: =E15/SQRT(2*(D15-1)) | T15: =COUNTIF('Метрики — ряд'!D10:AM10,"<"&L15) | U15: =COUNTIF('Метрики — ряд'!D10:AM10,"<"&M15)-T15 | V15: =COUNTIF('Метрики — ряд'!D10:AM10,"<"&C15)-T15-U15 | W15: =COUNTIF('Метрики — ряд'!D10:AM10,">="&C15) | X15: Решающая проверка: Завышение 68 %, та же причина
A16: ='Метрики — ряд'!A11 | B16: ='Метрики — ряд'!B11 | C16: ='Метрики — ряд'!C11 | D16: =COUNT('Метрики — ряд'!AO11:BW11) | E16: =STDEV('Метрики — ряд'!AO11:BW11) | F16: ='Расчёт'!G65 | G16: ='Расчёт'!H65 | H16: ='Расчёт'!C65 | I16: =IF(LEFT('Расчёт'!N65,6)="ЗАМЕНА","ист. симуляция","M(T) = z·σ·√T") | J16: =z_p*E16*SQRT(4) | K16: =z_p*E16*SQRT(1) | L16: =C16-J16 | M16: =C16-K16 | N16: =L16/C16*100 | O16: =M16/C16*100 | P16: ='Метрики — ряд'!AM11 | Q16: =IF(P16>=C16,"НАРУШЕНИЕ",IF(P16>=M16,"КРАСНАЯ",IF(P16>=L16,"ЖЁЛТАЯ","зелёная"))) | R16: =(C16-P16)/E16 | S16: =E16/SQRT(2*(D16-1)) | T16: =COUNTIF('Метрики — ряд'!D11:AM11,"<"&L16) | U16: =COUNTIF('Метрики — ряд'!D11:AM11,"<"&M16)-T16 | V16: =COUNTIF('Метрики — ряд'!D11:AM11,"<"&C16)-T16-U16 | W16: =COUNTIF('Метрики — ряд'!D11:AM11,">="&C16) | X16: Решающая проверка: Завышение 523 % — крайний случай сноса: четырёхмесячный рост почти отсутствует, весь ход направлен вниз
A17: ='Метрики — ряд'!A12 | B17: ='Метрики — ряд'!B12 | C17: ='Метрики — ряд'!C12 | D17: =COUNT('Метрики — ряд'!AO12:BW12) | E17: =STDEV('Метрики — ряд'!AO12:BW12) | F17: ='Расчёт'!G66 | G17: ='Расчёт'!H66 | H17: ='Расчёт'!C66 | I17: =IF(LEFT('Расчёт'!N66,6)="ЗАМЕНА","ист. симуляция","M(T) = z·σ·√T") | J17: =z_p*E17*SQRT(4) | K17: =z_p*E17*SQRT(1) | L17: =C17-J17 | M17: =C17-K17 | N17: =L17/C17*100 | O17: =M17/C17*100 | P17: ='Метрики — ряд'!AM12 | Q17: =IF(P17>=C17,"НАРУШЕНИЕ",IF(P17>=M17,"КРАСНАЯ",IF(P17>=L17,"ЖЁЛТАЯ","зелёная"))) | R17: =(C17-P17)/E17 | S17: =E17/SQRT(2*(D17-1)) | T17: =COUNTIF('Метрики — ряд'!D12:AM12,"<"&L17) | U17: =COUNTIF('Метрики — ряд'!D12:AM12,"<"&M17)-T17 | V17: =COUNTIF('Метрики — ряд'!D12:AM12,"<"&C17)-T17-U17 | W17: =COUNTIF('Метрики — ряд'!D12:AM12,">="&C17) | X17: Решающая проверка: Расхождение −19 %, внутри порога по модулю, но со знаком «минус»: модель чуть уже факта. Остаётся на M(T), отмечено
A18: ='Метрики — ряд'!A13 | B18: ='Метрики — ряд'!B13 | C18: ='Метрики — ряд'!C13 | D18: =COUNT('Метрики — ряд'!AO13:BW13) | E18: =STDEV('Метрики — ряд'!AO13:BW13) | F18: ='Расчёт'!G67 | G18: ='Расчёт'!H67 | H18: ='Расчёт'!C67 | I18: =IF(LEFT('Расчёт'!N67,6)="ЗАМЕНА","ист. симуляция","M(T) = z·σ·√T") | J18: =z_p*E18*SQRT(4) | K18: =z_p*E18*SQRT(1) | L18: =C18-J18 | M18: =C18-K18 | N18: =L18/C18*100 | O18: =M18/C18*100 | P18: ='Метрики — ряд'!AM13 | Q18: =IF(P18>=C18,"НАРУШЕНИЕ",IF(P18>=M18,"КРАСНАЯ",IF(P18>=L18,"ЖЁЛТАЯ","зелёная"))) | R18: =(C18-P18)/E18 | S18: =E18/SQRT(2*(D18-1)) | T18: =COUNTIF('Метрики — ряд'!D13:AM13,"<"&L18) | U18: =COUNTIF('Метрики — ряд'!D13:AM13,"<"&M18)-T18 | V18: =COUNTIF('Метрики — ряд'!D13:AM13,"<"&C18)-T18-U18 | W18: =COUNTIF('Метрики — ряд'!D13:AM13,">="&C18) | X18: Решающая проверка: Завышение 92 %, снос вниз
A20: Одиннадцать метрик на M(T), одна на замене — а не девять | B20: Формально нормальны три из двенадцати, но формальная проверка не решает: M(T) опирается на СУММУ T приращений, которая по ЦПТ ближе к нормальной. Решающая проверка (колонка I, вердикт с листа «Расчёт») показывает, что модель НИГДЕ не занижает буфер — она его завышает, и причина не в хвостах, а в сносе: EL и PD падают три года, а M(T) считает снос нулевым. Завышение безопасно, и снос в зачёт сознательно не берётся. Замена понадобилась одной метрике — CoR КБ/ПБ, где буфер на цикл реагирования не помещался в сам лимит.
A21: Почему CoR занимает две строки | B21: У режимной разметки две пары границ, и свернуть их в одну нельзя: именно это сворачивание и дало ошибку, из-за которой КБ/ПБ числилась жёлтой. В обычные месяцы граница зелёной 1,5727, в окне закрытия 0,7306 — вдвое ниже при том же лимите. Точка ряда сравнивается с границей СВОЕГО месяца, поэтому счётчики зон в T–W считаются раздельно по режимам: 28 + 2 обычных и 6 закрытия дают те же 36 точек.
A22: В окне закрытия зон не три, а две | B22: Q90 четырёхмесячных изменений там МЕНЬШЕ месячного (снос съедает рост на длинном окне), поэтому граница зелёной совпала с жёлтой после выправления через МАКС. И наблюдений там шесть — три года по два месяца. Квантиль 0,90 по шести есть фактически максимум выборки. Это свойство метода, и подавать его надо вместе с числом.
A23: Единого процента лимита не существует | B23: Колонка N разбегается от 24,4 % (CoR КБ/ПБ в окне закрытия) до 99,1 % (PD необеспеченные товарные). Граница в процентах лимита зависит от волатильности относительно лимита: у PD и EL σ крошечная, им граница нужна вплотную; у CoR и топ-20 σ большая. Любой единый порог — компромисс, а не калибровка.
A24: Расстояние до лимита в собственных σ каждой метрики. Цвет столбика получен из колонки O этого же листа через границы z·√1 и z·√4, поэтому он совпадает с колонкой N по построению. Утилизация слева показана рядом нарочно: у CoR КБ/ПБ она отрицательна, а метрика — вторая ближайшая к лимиту.

Sheet Триггеры
A1: Триггеры на движение: ΔСК ≤ −3 % или ΔЗайм ≥ +5 % за месяц
A2: Срабатывают независимо от зоны. Все 35 приростов показаны целиком — выборка из шести строк недоказуема: по ней не видно, что остальные 29 условию не отвечают.
A4: Дата | B4: ΔСК, % | C4: ΔЗайм, % | D4: Коэффициент | E4: Что сработало
A5: ='Ряд'!A6 | B5: ='Ряд'!K6 | C5: ='Ряд'!L6 | D5: ='Ряд'!H6 | E5: ='Ряд'!M6
A6: ='Ряд'!A7 | B6: ='Ряд'!K7 | C6: ='Ряд'!L7 | D6: ='Ряд'!H7 | E6: ='Ряд'!M7
A7: ='Ряд'!A8 | B7: ='Ряд'!K8 | C7: ='Ряд'!L8 | D7: ='Ряд'!H8 | E7: ='Ряд'!M8
A8: ='Ряд'!A9 | B8: ='Ряд'!K9 | C8: ='Ряд'!L9 | D8: ='Ряд'!H9 | E8: ='Ряд'!M9
A9: ='Ряд'!A10 | B9: ='Ряд'!K10 | C9: ='Ряд'!L10 | D9: ='Ряд'!H10 | E9: ='Ряд'!M10
A10: ='Ряд'!A11 | B10: ='Ряд'!K11 | C10: ='Ряд'!L11 | D10: ='Ряд'!H11 | E10: ='Ряд'!M11
A11: ='Ряд'!A12 | B11: ='Ряд'!K12 | C11: ='Ряд'!L12 | D11: ='Ряд'!H12 | E11: ='Ряд'!M12
A12: ='Ряд'!A13 | B12: ='Ряд'!K13 | C12: ='Ряд'!L13 | D12: ='Ряд'!H13 | E12: ='Ряд'!M13
A13: ='Ряд'!A14 | B13: ='Ряд'!K14 | C13: ='Ряд'!L14 | D13: ='Ряд'!H14 | E13: ='Ряд'!M14
A14: ='Ряд'!A15 | B14: ='Ряд'!K15 | C14: ='Ряд'!L15 | D14: ='Ряд'!H15 | E14: ='Ряд'!M15
A15: ='Ряд'!A16 | B15: ='Ряд'!K16 | C15: ='Ряд'!L16 | D15: ='Ряд'!H16 | E15: ='Ряд'!M16
A16: ='Ряд'!A17 | B16: ='Ряд'!K17 | C16: ='Ряд'!L17 | D16: ='Ряд'!H17 | E16: ='Ряд'!M17
... A39: ='Ряд'!A40 | B39: ='Ряд'!K40 | C39: ='Ряд'!L40 | D39: ='Ряд'!H40 | E39: ='Ряд'!M40
A41: Сработало | B41: =COUNTIF(E5:E39,"Займ")+COUNTIF(E5:E39,"СК")+COUNTIF(E5:E39,"оба") | C41: =B41/35*100 | D41: из 35 приростов, %
A43: Строка 01.2026 — та, ради которой триггеры и заводятся: вход сделан капиталом (ΔСК = −7,92 %), а не портфелем, и уровневая зона его не предупреждала в принципе. Зона смотрит на значение коэффициента, триггер — на его движение. Формула M(T) описывает диффузию, триггер ловит скачок; ни один из двух инструментов не заменяет другой.
A44: Триггеры на движение по всем двенадцати метрикам
A45: Порог берётся из собственной строки метрики на листе «Метрики»: T1 — колонка K (буфер на месяц), T2 — колонка J (буфер на цикл). У метрик на M(T) порог параметрический, у CoR — эмпирический, то есть триггер меняется вместе с методом разметки. Калибровки на исходах нет и быть не может: превышений лимита в ряде одно.
A46: Метрика | B46: Порог T1 (мес.) | C46: Сработок T1 | D46: Порог T2 (3 мес.) | E46: Сработок T2 | F46: T1, % месяцев | G46: Макс. Δ за месяц | H46: Макс. Δ за 3 мес
A47: Топ-20 / СК | B47: ='Метрики'!K5 | C47: =COUNTIF('Ряд'!J6:J40,">="&B47) | D47: ='Метрики'!J5 | E47: =COUNTIF('Ряд'!AF9:AF40,">="&D47) | F47: =C47/COUNT('Ряд'!J6:J40)*100 | G47: =MAX('Ряд'!J6:J40) | H47: =MAX('Ряд'!AF9:AF40)
A48: CoR КБ/ПБ | B48: ='Метрики'!K6 | C48: =COUNTIF('Ряд'!P6:P40,">="&B48) | D48: ='Метрики'!J6 | E48: =COUNTIF('Ряд'!W9:W40,">="&D48) | F48: =C48/COUNT('Ряд'!P6:P40)*100 | G48: =MAX('Ряд'!P6:P40) | H48: =MAX('Ряд'!W9:W40)
A49: CoR МСБ | B49: ='Метрики'!K8 | C49: =COUNTIF('Ряд'!S6:S40,">="&B49) | D49: ='Метрики'!J8 | E49: =COUNTIF('Ряд'!AC9:AC40,">="&D49) | F49: =C49/COUNT('Ряд'!S6:S40)*100 | G49: =MAX('Ряд'!S6:S40) | H49: =MAX('Ряд'!AC9:AC40)
A50: EL — всего | B50: ='Метрики'!K10 | C50: =COUNTIF('Метрики — ряд'!AO5:BW5,">="&B50) | D50: ='Метрики'!J10 | E50: =COUNTIF('Метрики — ряд'!BY5:DD5,">="&D50) | F50: =C50/COUNT('Метрики — ряд'!AO5:BW5)*100 | G50: =MAX('Метрики — ряд'!AO5:BW5) | H50: =MAX('Метрики — ряд'!BY5:DD5)
A51: EL — необеспеченные | B51: ='Метрики'!K11 | C51: =COUNTIF('Метрики — ряд'!AO6:BW6,">="&B51) | D51: ='Метрики'!J11 | E51: =COUNTIF('Метрики — ряд'!BY6:DD6,">="&D51) | F51: =C51/COUNT('Метрики — ряд'!AO6:BW6)*100 | G51: =MAX('Метрики — ряд'!AO6:BW6) | H51: =MAX('Метрики — ряд'!BY6:DD6)
A52: EL — обеспеченные | B52: ='Метрики'!K12 | C52: =COUNTIF('Метрики — ряд'!AO7:BW7,">="&B52) | D52: ='Метрики'!J12 | E52: =COUNTIF('Метрики — ряд'!BY7:DD7,">="&D52) | F52: =C52/COUNT('Метрики — ряд'!AO7:BW7)*100 | G52: =MAX('Метрики — ряд'!AO7:BW7) | H52: =MAX('Метрики — ряд'!BY7:DD7)
A53: EL — прочие | B53: ='Метрики'!K13 | C53: =COUNTIF('Метрики — ряд'!AO8:BW8,">="&B53) | D53: ='Метрики'!J13 | E53: =COUNTIF('Метрики — ряд'!BY8:DD8,">="&D53) | F53: =C53/COUNT('Метрики — ряд'!AO8:BW8)*100 | G53: =MAX('Метрики — ряд'!AO8:BW8) | H53: =MAX('Метрики — ряд'!BY8:DD8)
A54: PD — необеспеченные | B54: ='Метрики'!K14 | C54: =COUNTIF('Метрики — ряд'!AO9:BW9,">="&B54) | D54: ='Метрики'!J14 | E54: =COUNTIF('Метрики — ряд'!BY9:DD9,">="&D54) | F54: =C54/COUNT('Метрики — ряд'!AO9:BW9)*100 | G54: =MAX('Метрики — ряд'!AO9:BW9) | H54: =MAX('Метрики — ряд'!BY9:DD9)
A55: PD — необеспеченные, наличные | B55: ='Метрики'!K15 | C55: =COUNTIF('Метрики — ряд'!AO10:BW10,">="&B55) | D55: ='Метрики'!J15 | E55: =COUNTIF('Метрики — ряд'!BY10:DD10,">="&D55) | F55: =C55/COUNT('Метрики — ряд'!AO10:BW10)*100 | G55: =MAX('Метрики — ряд'!AO10:BW10) | H55: =MAX('Метрики — ряд'!BY10:DD10)
A56: PD — необеспеченные, товарные | B56: ='Метрики'!K16 | C56: =COUNTIF('Метрики — ряд'!AO11:BW11,">="&B56) | D56: ='Метрики'!J16 | E56: =COUNTIF('Метрики — ряд'!BY11:DD11,">="&D56) | F56: =C56/COUNT('Метрики — ряд'!AO11:BW11)*100 | G56: =MAX('Метрики — ряд'!AO11:BW11) | H56: =MAX('Метрики — ряд'!BY11:DD11)
A57: PD — обеспеченные | B57: ='Метрики'!K17 | C57: =COUNTIF('Метрики — ряд'!AO12:BW12,">="&B57) | D57: ='Метрики'!J17 | E57: =COUNTIF('Метрики — ряд'!BY12:DD12,">="&D57) | F57: =C57/COUNT('Метрики — ряд'!AO12:BW12)*100 | G57: =MAX('Метрики — ряд'!AO12:BW12) | H57: =MAX('Метрики — ряд'!BY12:DD12)
A58: PD — прочие | B58: ='Метрики'!K18 | C58: =COUNTIF('Метрики — ряд'!AO13:BW13,">="&B58) | D58: ='Метрики'!J18 | E58: =COUNTIF('Метрики — ряд'!BY13:DD13,">="&D58) | F58: =C58/COUNT('Метрики — ряд'!AO13:BW13)*100 | G58: =MAX('Метрики — ряд'!AO13:BW13) | H58: =MAX('Метрики — ряд'!BY13:DD13)
A60: Триггер и зона ловят разное, и ни один не заменяет другой | B60: Зона смотрит на УРОВЕНЬ метрики, триггер — на её ДВИЖЕНИЕ. Формула буфера описывает диффузию, триггер ловит скачок. Январский вход топ-20 в красную зону сделан капиталом, и уровневая зона не предупреждала о нём в принципе — ровно поэтому триггеры и заводятся.
A61: Порог не новое число, а тот же буфер | B61: T1 равен буферу на месяц, T2 — буферу на цикл реагирования. Это сознательно: вводить отдельно калиброванный порог было бы нечем обосновать. Побочное следствие полезное: у CoR порог эмпирический, потому что эмпирична сама разметка, — триггер наследует метод автоматически.
A62: Чего эти числа НЕ означают | B62: Столбцы «сработок» — это частота, а не доля верных сигналов. Калибровка на исходах невозможна: превышение лимита в ряде одно (топ-20, 05.2026), у остальных одиннадцати метрик их ноль. Пять эпизодов 2016–2017 были при уровне 250 %, а не 95, и к сегодняшнему порогу неприменимы.
